{"type":"Feature",
 "geometry":{"type":"Point","coordinates":[-120.795060375565,37.8021510740049]},
 "properties":{"prmname":"HSU302D16",
 "description":"Hidden node on surface water conveyance channel",
 "type":"Junction",
 "inflows":null,
 "sinks":null,
 "flow":null}}
