{"type":"Feature",
 "geometry":{"type":"Point","coordinates":[-120.976730847159,37.7272953936576]},
 "properties":{"prmname":"HSU302D16",
 "description":"Hidden node on surface water conveyance channel",
 "type":"Junction",
 "inflows":null,
 "sinks":null,
 "flow":null}}
