{"type":"Feature",
 "geometry":{"type":"Point","coordinates":[-120.976730630831,37.7237425310498]},
 "properties":{"prmname":"HSU302D16",
 "description":"Hidden node on surface water conveyance channel",
 "type":"Junction",
 "inflows":null,
 "sinks":null,
 "flow":null}}
