{"type":"Feature",
 "geometry":{"type":"Point","coordinates":[-121.139396298091,38.0576188365164]},
 "properties":{"prmname":"INT STOCK",
 "description":"DAU 182 interior urban flows",
 "type":"Urban Demand",
 "inflows":null,
 "sinks":null,
 "flow":null}}
