{"type":"Feature",
 "geometry":{"type":"Point","coordinates":[-121.137150509881,38.0558505012285]},
 "properties":{"prmname":"INT STOCK",
 "description":"DAU 182 interior urban flows",
 "type":"Urban Demand",
 "inflows":null,
 "sinks":null,
 "flow":null}}
