{"type":"Feature",
 "geometry":{"type":"Point","coordinates":[-118.75092451635,34.6329867214887]},
 "properties":{"prmname":"SR-PYM",
 "description":"Pyramid Lake",
 "type":"Surface Storage",
 "initialstorage":170,
 "endingstorage":143.94,
 "areacapfactor":0.00725,
 "inflows":null,
 "evaporation":{"$ref" : "evaporation.csv"},
 "el_ar_cap":{"$ref" : "elevation_area_capacity.csv"},
 "costs":{ "type":"Monthly Variable","costs":{"JAN":{"$ref":"costs/JAN.csv"},"FEB":{"$ref":"costs/FEB.csv"},"MAR":{"$ref":"costs/MAR.csv"},"APR":{"$ref":"costs/APR.csv"},"MAY":{"$ref":"costs/MAY.csv"},"JUN":{"$ref":"costs/JUN.csv"},"JUL":{"$ref":"costs/JUL.csv"},"AUG":{"$ref":"costs/AUG.csv"},"SEP":{"$ref":"costs/SEP.csv"},"OCT":{"$ref":"costs/OCT.csv"},"NOV":{"$ref":"costs/NOV.csv"},"DEC":{"$ref":"costs/DEC.csv"}}},
 "bounds":[{"type":"LBC","bound":4.8},{"type":"UBC","bound":171.2}],
 "sinks":null}}
