{"type":"Feature",
 "geometry":{"type":"Point","coordinates":[-121.871843131067,39.1833552384542]},
 "properties":{"prmname":"HSD103A",
 "description":"Hidden surface water calibration node",
 "type":"Junction",
 "inflows":null,
 "sinks":null,
 "flow":{"$ref" : "flow.csv"}}}
