{"type":"Feature",
 "geometry":{"type":"Point","coordinates":[-118.502208252786,34.5288487166782]},
 "properties":{"prmname":"HNP503",
 "description":null,
 "type":"Junction",
 "inflows":null,
 "sinks":null,
 "flow":null}}
