{"type":"Feature",
 "geometry":{"type":"Point","coordinates":[-118.504454040996,34.525148290126]},
 "properties":{"prmname":"HNP503",
 "description":null,
 "type":"Junction",
 "inflows":null,
 "sinks":null,
 "flow":null}}
