{"type":"Feature",
 "geometry":{"type":"Point","coordinates":[-118.552719576421,34.4292377985629]},
 "properties":{"prmname":"HNP503",
 "description":null,
 "type":"Junction",
 "inflows":null,
 "sinks":null,
 "flow":null}}
