{"type":"Feature",
 "geometry":{"type":"Point","coordinates":[-118.499962464575,34.5325489788068]},
 "properties":{"prmname":"HNP503",
 "description":null,
 "type":"Junction",
 "inflows":null,
 "sinks":null,
 "flow":null}}
