{"type":"Feature",
 "geometry":{"type":"Point","coordinates":[-117.122863913518,33.5830254343641]},
 "properties":{"prmname":"SR-SKN",
 "description":"Lake Skinner input because of its separation of nodes and wq importance",
 "type":"Surface Storage",
 "initialstorage":33.8,
 "endingstorage":33.8,
 "areacapfactor":0.0279,
 "inflows":null,
 "evaporation":{"$ref" : "evaporation.csv"},
 "el_ar_cap":{"$ref":"elevation_area_capacity.csv"},
 "costs":{ "type":"Annual Variable","costs":{"JAN-DEC":{"$ref":"costs/JAN-DEC.csv"}}},
 "bounds":[{"type":"LBC","bound":33.8},{"type":"UBC","bound":44}],
 "sinks":null}}
