{
  "type": "Feature",
  "geometry": {
    "type": "Point",
    "coordinates": [
      -121.022053113809,
      38.2249175915377
    ]
  },
  "properties": {
    "prmname": "SR-CR",
    "description": "Camanche Res",
    "type": "Surface Storage",
    "origins": [
      "SR-PR",
      "CN2"
    ],
    "terminals": [
      "C38"
    ],
    "initialstorage": 200,
    "endingstorage": 235,
    "areacapfactor": 0.005604,
    "inflows": null,
    "el_ar_cap": {
      "$ref": "el_ar_cap.csv"
    },
    "costs": {
      "type": "Monthly Variable",
      "costs": [
        {
          "label": "JAN",
          "costs": [
            {
              "capacity": 0,
              "cost": 6.55999994277954
            },
            {
              "capacity": 328,
              "cost": 0
            }
          ]
        },
        {
          "label": "FEB",
          "costs": [
            {
              "capacity": 0,
              "cost": 6.46000003814697
            },
            {
              "capacity": 323,
              "cost": 0
            }
          ]
        },
        {
          "label": "MAR",
          "costs": [
            {
              "capacity": 0,
              "cost": 6.88000011444092
            },
            {
              "capacity": 344,
              "cost": 0
            }
          ]
        },
        {
          "label": "APR",
          "costs": [
            {
              "capacity": 0,
              "cost": 7.71999979019165
            },
            {
              "capacity": 386,
              "cost": 0
            }
          ]
        },
        {
          "label": "MAY",
          "costs": [
            {
              "capacity": 0,
              "cost": 8.76000022888184
            },
            {
              "capacity": 438,
              "cost": 0
            }
          ]
        },
        {
          "label": "JUN",
          "costs": [
            {
              "capacity": 0,
              "cost": 8.61999988555908
            },
            {
              "capacity": 431,
              "cost": 0
            }
          ]
        },
        {
          "label": "JUL",
          "costs": [
            {
              "capacity": 0,
              "cost": 8.61999988555908
            },
            {
              "capacity": 431,
              "cost": 0
            }
          ]
        },
        {
          "label": "AUG",
          "costs": [
            {
              "capacity": 0,
              "cost": 8.61999988555908
            },
            {
              "capacity": 431,
              "cost": 0
            }
          ]
        },
        {
          "label": "SEP",
          "costs": [
            {
              "capacity": 0,
              "cost": 7.90000009536743
            },
            {
              "capacity": 395,
              "cost": 0
            }
          ]
        },
        {
          "label": "OCT",
          "costs": [
            {
              "capacity": 0,
              "cost": 6.51999998092651
            },
            {
              "capacity": 326,
              "cost": 0
            }
          ]
        },
        {
          "label": "NOV",
          "costs": [
            {
              "capacity": 0,
              "cost": 6.3600001335144
            },
            {
              "capacity": 318,
              "cost": 0
            }
          ]
        },
        {
          "label": "DEC",
          "costs": [
            {
              "capacity": 0,
              "cost": 6.46000003814697
            },
            {
              "capacity": 323,
              "cost": 0
            }
          ]
        }
      ]
    },
    "constraints": {
      "constraint_type": "Bounded",
      "lower": {
        "bound_type": "Constant",
        "bound": 4
      },
      "upper": {
        "$ref": "constraints_upper_date.csv"
      }
    }
  }
}