{"type":"Feature",
 "geometry":{"type":"Point","coordinates":[-118.485596784053,34.5550574955173]},
 "properties":{"prmname":"HGRVC",
 "description":null,
 "type":"Junction",
 "inflows":null,
 "sinks":null,
 "flow":null}}
