{"type":"Feature",
 "geometry":{"type":"Point","coordinates":[-119.196961,34.281464]},
 "properties":{"prmname":"HGRVC",
 "description":null,
 "type":"Junction",
 "inflows":null,
 "sinks":null,
 "flow":null}}
