{"type":"Feature",
 "geometry":{"type":"Point","coordinates":[-119.041222087827,34.4263093127776]},
 "properties":{"prmname":"HGRVC",
 "description":null,
 "type":"Junction",
 "inflows":null,
 "sinks":null,
 "flow":null}}
