{"type":"Feature",
 "geometry":{"type":"Point","coordinates":[-118.485597,34.555057]},
 "properties":{"prmname":"HGRVC",
 "description":null,
 "type":"Junction",
 "inflows":null,
 "sinks":null,
 "flow":null}}
