{
  "type": "Feature",
  "geometry": {
    "type": "Point",
    "coordinates": [
      -119.25688829045,
      36.0603446135928
    ]
  },
  "properties": {
    "prmname": "Sink T25",
    "description": "Sink from Fresno",
    "type": "Sink",
    "origins": null,
    "terminals": null,
    "inflows": null
  }
}