{"type":"Feature",
 "geometry":{"type":"Point","coordinates":[-120.947631505286,38.7881386379463]},
 "properties":{"prmname":"WWP204",
 "description":"Sacramento OUT",
 "type":"Water Treatment",
 "inflows":null,
 "sinks":null,
 "flow":null}}
