{"type":"Feature",
 "geometry":{"type":"Point","coordinates":[-122.117807583529,37.8150169196961]},
 "properties":{"prmname":"IND EBMUD",
 "description":"Parts of DAU 46 & 47",
 "type":"Urban Demand",
 "inflows":null,
 "sinks":null}}
