{"type":"Feature",
 "geometry":{"type":"Point","coordinates":[-117.458835576469,35.634277815831]},
 "properties":{"prmname":"HXI502",
 "description":null,
 "type":"Junction",
 "inflows":null,
 "sinks":null,
 "flow":null}}
