{"type":"Feature",
 "geometry":{"type":"Point","coordinates":[-120.945251553007,37.4301137925117]},
 "properties":{"prmname":"HSD303",
 "description":"Hidden surface water calibration node",
 "type":"Junction",
 "inflows":null,
 "sinks":null,
 "flow":null}}
