{"type":"Feature",
 "geometry":{"type":"Point","coordinates":[-120.676336849365,35.2735440840847]},
 "properties":{"prmname":"HNP406",
 "description":null,
 "type":"Junction",
 "inflows":null,
 "sinks":null,
 "flow":null}}
