{"type":"Feature",
 "geometry":{"type":"Point","coordinates":[-120.676336576421,35.2735444472212]},
 "properties":{"prmname":"HNP406",
 "description":null,
 "type":"Junction",
 "inflows":null,
 "sinks":null,
 "flow":null}}
