{
  "type": "Feature",
  "geometry": {
    "type": "Point",
    "coordinates": [
      -117.862728451475,
      34.0343816478517
    ]
  },
  "properties": {
    "prmname": "IRes CMWD",
    "description": "DAUs 87,89,90.92,96,114 and part of 100 - Urban Demand for Interior Res/Comm",
    "type": "Urban Demand",
    "origins": [
      "T5CMWD"
    ],
    "terminals": [
      "T10CMWD"
    ],
    "inflows": null
  }
}