{"type":"Feature",
 "geometry":{"type":"Point","coordinates":[-121.059532326993,38.6533121727661]},
 "properties":{"prmname":"HGP07",
 "description":"Hidden node for calibration of GW-7",
 "type":"Junction",
 "inflows":null,
 "sinks":null,
 "flow":{"$ref" : "flow.csv"}}}
