{"type":"Feature",
 "geometry":{"type":"Point","coordinates":[-115.651577072913,33.1495469886771]},
 "properties":{"prmname":"HSD510",
 "description":null,
 "type":"Junction",
 "inflows":null,
 "sinks":null,
 "flow":null}}
