{
  "type": "Feature",
  "geometry": {
    "type": "Point",
    "coordinates": [
      -122.187346354897,
      39.2606714671897
    ]
  },
  "properties": {
    "prmname": "CVPM3",
    "description": "CVPM3 Agricultural Demand",
    "type": "Agricultural Demand",
    "origins": [
      "HSU3D66",
      "HSU3C305",
      "C302",
      "HGP3"
    ],
    "terminals": [
      "C305",
      "GW-3"
    ],
    "costs": {
      "type": "Monthly Variable",
      "costs": {
        "$ref": "costs_costs.json"
      }
    },
    "constraints": {
      "constraint_type": "Bounded",
      "lower": null,
      "upper": {
        "bound_type": "TimeSeries",
        "date": {
          "$ref": "constraints_upper_date.json"
        },
        "bound": {
          "$ref": "constraints_upper_bound.json"
        }
      }
    }
  }
}