{"type":"Feature",
 "geometry":{"type":"Point","coordinates":[-118.508418845802,34.2820253213857]},
 "properties":{"prmname":"HGPVC",
 "description":"",
 "type":"Junction",
 "inflows":null,
 "sinks":null}}
