{"type":"Feature",
 "geometry":{"type":"Point","coordinates":[-121.842669,39.333184]},
 "properties":{"prmname":"HSUR201",
 "description":"Hidden node for supply into the Gray Lodge Refuge",
 "type":"Junction",
 "inflows":null,
 "sinks":null,
 "flow":null}}
