{"type":"Feature",
 "geometry":{"type":"Point","coordinates":[-121.703082105707,39.2015096609161]},
 "properties":{"prmname":"HSUR201",
 "description":"Hidden node for supply into the Gray Lodge Refuge",
 "type":"Junction",
 "inflows":null,
 "sinks":null,
 "flow":null}}
