{
  "type": "Feature",
  "geometry": {
    "type": "Point",
    "coordinates": [
      -116.073289638695,
      33.5675989080449
    ]
  },
  "properties": {
    "prmname": "HUDCH",
    "description": "Hidden node for coachella Ag",
    "type": "Junction",
    "origins": [
      "C147"
    ],
    "terminals": [
      "AGS COACH",
      "AGG COACH"
    ],
    "inflows": null
  }
}