{"type":"Feature",
 "geometry":{"type":"Point","coordinates":[-116.725443824862,33.0789738446281]},
 "properties":{"prmname":"WTP511",
 "description":"",
 "type":"Water Treatment",
 "inflows":null,
 "sinks":null}}
