{"type":"Feature",
 "geometry":{"type":"Point","coordinates":[-119.650665458592,36.6248872809863]},
 "properties":{"prmname":"HSU403C53",
 "description":"Hidden node on surface water conveyance channel",
 "type":"Junction",
 "inflows":null,
 "sinks":null,
 "flow":null}}
