{
  "type": "Feature",
  "geometry": {
    "type": "Point",
    "coordinates": [
      -118.095503144919,
      34.8044354111839
    ]
  },
  "properties": {
    "prmname": "GW-AV",
    "description": "Antelope Valley Groundwater",
    "type": "Groundwater Storage",
    "origins": [
      "D868",
      "T33AV",
      "EXT AV"
    ],
    "terminals": [
      "T6AV"
    ],
    "initialstorage": 20000,
    "endingstorage": 20000,
    "inflows": [
      {
        "name": "Antelope_Valley",
        "date": {
          "$ref": "inflows_0_date.json"
        },
        "inflow": {
          "$ref": "inflows_0_inflow.json"
        }
      }
    ],
    "costs": {
      "type": "Constant",
      "cost": 0
    },
    "constraints": {
      "constraint_type": "Bounded",
      "lower": {
        "bound_type": "None"
      },
      "upper": {
        "bound_type": "Constant",
        "bound": 68000
      }
    }
  }
}