{"type":"Feature",
 "geometry":{"type":"Point","coordinates":[-121.681961589886,39.0870604787995]},
 "properties":{"prmname":"HSD202",
 "description":"Hidden surface water calibration node",
 "type":"Junction",
 "inflows":null,
 "sinks":null}}
