{"type":"Feature",
 "geometry":{"type":"Point","coordinates":[-120.483107847159,37.2843566815219]},
 "properties":{"prmname":"HSU401C53",
 "description":"Hidden node on surface water conveyance channel",
 "type":"Junction",
 "inflows":null,
 "sinks":null,
 "flow":null}}
