{
  "type": "Feature",
  "geometry": {
    "type": "Point",
    "coordinates": [
      -120.171511637999,
      34.8039696600582
    ]
  },
  "properties": {
    "prmname": "INT SB-SLO",
    "description": "Only the SWP Imports are modeled (DAU 67, 68, 71, 74, 75)",
    "type": "Urban Demand",
    "origins": [
      "T71"
    ],
    "terminals": [
      "T72"
    ],
    "inflows": null
  }
}