{
  "type": "Feature",
  "geometry": {
    "type": "Point",
    "coordinates": [
      -118.721155680043,
      34.8121254100938
    ]
  },
  "properties": {
    "prmname": "OSO PMP",
    "description": "West Branch SWP Pumping Plant",
    "type": "Pump Plant",
    "origins": [
      "D865"
    ],
    "terminals": [
      "D884"
    ],
    "inflows": null
  }
}