{"type":"Feature",
 "geometry":{"type":"Point","coordinates":[-120.924679294535,37.734723850348]},
 "properties":{"prmname":"EXT CVPM11",
 "description":"100% of DAU 205 & 206, exterior",
 "type":"Urban Demand",
 "inflows":null,
 "sinks":null,
 "flow":null}}
