{"type":"Feature",
 "geometry":{"type":"Point","coordinates":[-121.910776389003,39.096726377512]},
 "properties":{"prmname":"EXT CVPM04",
 "description":"100% of DAU 164, exterior",
 "type":"Agricultural Demand",
 "inflows":null,
 "sinks":null,
 "flow":null}}
