{"type":"Feature",
 "geometry":{"type":"Point","coordinates":[-121.913022177213,39.0984692727642]},
 "properties":{"prmname":"EXT CVPM04",
 "description":"100% of DAU 164, exterior",
 "type":"Agricultural Demand",
 "inflows":null,
 "sinks":null,
 "flow":null}}
