{"type":"Feature",
 "geometry":{"type":"Point","coordinates":[-119.25688829045,36.0603446135928]},
 "properties":{"prmname":"Sink C52",
 "description":"Depletion from South Fork of Kings River",
 "type":"Sink",
 "inflows":null,
 "sinks":null}}
