{"type":"Feature",
 "geometry":{"type":"Point","coordinates":[-118.998229653251,36.1204567517145]},
 "properties":{"prmname":"Sink CN4",
 "description":"Calibration Flow Sink Node",
 "type":"Sink",
 "inflows":null,
 "sinks":null}}
