{"type":"Feature",
 "geometry":{"type":"Point","coordinates":[-120.317759847159,37.1317058266282]},
 "properties":{"prmname":"HSU306C72",
 "description":"Hidden node on surface water conveyance channel",
 "type":"Junction",
 "inflows":null,
 "sinks":null,
 "flow":null}}
