{
  "type": "Feature",
  "geometry": {
    "type": "Point",
    "coordinates": [
      -120.342475847159,
      37.2733578981334
    ]
  },
  "properties": {
    "prmname": "HSU306C72",
    "description": "Hidden node on surface water conveyance channel",
    "type": "Junction",
    "inflows": null,
    "sinks": null,
    "flow": {
      "$ref": "flow.csv"
    }
  }
}