{"type":"Feature",
 "geometry":{"type":"Point","coordinates":[-117.614037619923,34.5547732837393]},
 "properties":{"prmname":"HXI506",
 "description":null,
 "type":"Junction",
 "inflows":null,
 "sinks":null,
 "flow":{"$ref" : "flow.csv"}}}
