{"type":"Feature",
 "geometry":{"type":"Point","coordinates":[-117.616283408133,34.5538484805961]},
 "properties":{"prmname":"HXI506",
 "description":null,
 "type":"Junction",
 "inflows":null,
 "sinks":null,
 "flow":{"$ref" : "flow.csv"}}}
