{"type":"Feature",
 "geometry":{"type":"Point","coordinates":[-117.374770576421,34.4849588737973]},
 "properties":{"prmname":"HXI506",
 "description":null,
 "type":"Junction",
 "inflows":null,
 "sinks":null,
 "flow":{"$ref" : "flow.csv"}}}
