{"type":"Feature",
 "geometry":{"type":"Point","coordinates":[-120.496582576421,37.2825698238413]},
 "properties":{"prmname":"HNP402",
 "description":null,
 "type":"Junction",
 "inflows":null,
 "sinks":null,
 "flow":null}}
