{"type":"Feature",
 "geometry":{"type":"Point","coordinates":[-122.098831500502,38.3149985455252]},
 "properties":{"prmname":"WWP205",
 "description":"Napa-Solano OUT",
 "type":"Water Treatment",
 "inflows":null,
 "sinks":null}}
