{"type":"Feature",
 "geometry":{"type":"Point","coordinates":[-117.460982,34.08128]},
 "properties":{"prmname":"GW_SBV",
 "description":"SBV groundwater",
 "type":"Groundwater Storage",
 "initialstorage":2500,
 "endingstorage":2500,
 "inflows":{"default":{"description":"Local inflows to GW","inflow":{"$ref" : "inflows/default.csv"}}},
 "storage":{"$ref" : "storage.csv"},
 "costs":{"type":"Constant",
 "cost":0},
 "bounds":[{"type":"UBC","bound":11620}],
 "sinks":null,
 "flow":null}}
