{
  "type": "Feature",
  "geometry": {
    "type": "Point",
    "coordinates": [
      -117.294960635369,
      34.5286221977562
    ]
  },
  "properties": {
    "prmname": "WTP505",
    "description": null,
    "type": "Water Treatment",
    "inflows": null,
    "sinks": null,
    "flow": {
      "$ref": "flow.csv"
    }
  }
}