{"type":"Feature",
 "geometry":{"type":"Point","coordinates":[-120.946653445382,37.732627164579]},
 "properties":{"prmname":"HNP302",
 "description":null,
 "type":"Junction",
 "inflows":null,
 "sinks":null,
 "flow":null}}
