{"type":"Feature",
 "geometry":{"type":"Point","coordinates":[-120.979843393034,37.7321799000616]},
 "properties":{"prmname":"HNP302",
 "description":null,
 "type":"Junction",
 "inflows":null,
 "sinks":null,
 "flow":null}}
