{"type":"Feature",
 "geometry":{"type":"Point","coordinates":[-114.468429889868,32.8725045073908]},
 "properties":{"prmname":"AgS_Bard",
 "description":"Bard Water District (Yuma)",
 "type":"Agricultural Demand",
 "inflows":null,
 "sinks":[{"AgS_Bard" : {"description":"Bard WD return flow","costs":{"type":"Constant",
 "cost":0},"bounds":[{"type":"NOB"}],"flow":{"$ref" : "./sinks/AgS_Bard/flow.csv"}}}],
 "flow":null}}
