{"type":"Feature",
 "geometry":{"type":"Point","coordinates":[-118.75092451635,34.6329867214887]},
 "properties":{"prmname":"SR-PYM",
 "description":"Pyramid Lake",
 "type":"Surface Storage",
 "initialstorage":170,
 "endingstorage":143.94,
 "areacapfactor":0.00725,
 "inflows":null,
 "el_ar_cap":{"$ref":"elevation_area_capacity.csv"},
 "costs":{ "type":"Monthly Variable","costs":{"JAN":{"$ref":"cost_JAN.csv"},"FEB":{"$ref":"cost_FEB.csv"},"MAR":{"$ref":"cost_MAR.csv"},"APR":{"$ref":"cost_APR.csv"},"MAY":{"$ref":"cost_MAY.csv"},"JUN":{"$ref":"cost_JUN.csv"},"JUL":{"$ref":"cost_JUL.csv"},"AUG":{"$ref":"cost_AUG.csv"},"SEP":{"$ref":"cost_SEP.csv"},"OCT":{"$ref":"cost_OCT.csv"},"NOV":{"$ref":"cost_NOV.csv"},"DEC":{"$ref":"cost_DEC.csv"}}},
 "bounds":[{"type":"LBC","bound":4.8},{"type":"UBC","bound":171.2}],
 "sinks":null}}
