{"type":"Feature",
 "geometry":{"type":"Point","coordinates":[-117.116496576421,33.715811971511]},
 "properties":{"prmname":"HXI509",
 "description":null,
 "type":"Junction",
 "inflows":null,
 "sinks":null,
 "flow":{"$ref" : "flow.csv"}}}
