{"type":"Feature",
 "geometry":{"type":"Point","coordinates":[-117.11649615805,33.7158116038262]},
 "properties":{"prmname":"HXI509",
 "description":null,
 "type":"Junction",
 "inflows":null,
 "sinks":null,
 "flow":{"$ref" : "flow.csv"}}}
