{"type":"Feature",
 "geometry":{"type":"Point","coordinates":[-117.11425036984,33.7167456231551]},
 "properties":{"prmname":"HXI509",
 "description":null,
 "type":"Junction",
 "inflows":null,
 "sinks":null,
 "flow":{"$ref" : "flow.csv"}}}
