{"type":"Feature",
 "geometry":{"type":"Point","coordinates":[-122.081882525557,38.515207095648]},
 "properties":{"prmname":"SR-BER",
 "description":"Lake Berryessa",
 "type":"Surface Storage",
 "initialstorage":806.3,
 "endingstorage":806.3,
 "areacapfactor":0.009746412,
 "inflows":null,
 "evaporation":{"$ref" : "evaporation.csv"},
 "el_ar_cap":{"$ref" : "elevation_area_capacity.csv"},
 "costs":{ "type":"Monthly Variable","costs":{"JAN":{"$ref":"costs/JAN.csv"},"FEB":{"$ref":"costs/FEB.csv"},"MAR":{"$ref":"costs/MAR.csv"},"APR":{"$ref":"costs/APR.csv"},"MAY":{"$ref":"costs/MAY.csv"},"JUN":{"$ref":"costs/JUN.csv"},"JUL":{"$ref":"costs/JUL.csv"},"AUG":{"$ref":"costs/AUG.csv"},"SEP":{"$ref":"costs/SEP.csv"},"OCT":{"$ref":"costs/OCT.csv"},"NOV":{"$ref":"costs/NOV.csv"},"DEC":{"$ref":"costs/DEC.csv"}}},
 "bounds":[{"type":"LBC","bound":10.3},{"type":"UBC","bound":1602.3}],
 "sinks":null}}
