{
  "type": "Feature",
  "geometry": {
    "type": "Point",
    "coordinates": [
      -121.546908746377,
      37.1214914153249
    ]
  },
  "properties": {
    "prmname": "SR-SCV",
    "description": "Santa Clara Aggregate",
    "type": "Surface Storage",
    "origins": null,
    "terminals": [
      "C315"
    ],
    "initialstorage": 94,
    "endingstorage": 94,
    "areacapfactor": 0.020407,
    "inflows": [
      {
        "$ref": "inflows_0.csv"
      }
    ],
    "el_ar_cap": null,
    "costs": {
      "type": "Monthly Variable",
      "costs": [
        {
          "label": "JAN",
          "costs": [
            {
              "capacity": 0,
              "cost": 3.40000009536743
            },
            {
              "capacity": 170,
              "cost": 0
            }
          ]
        },
        {
          "label": "FEB",
          "costs": [
            {
              "capacity": 0,
              "cost": 3.40000009536743
            },
            {
              "capacity": 170,
              "cost": 0
            }
          ]
        },
        {
          "label": "MAR",
          "costs": [
            {
              "capacity": 0,
              "cost": 3.40000009536743
            },
            {
              "capacity": 170,
              "cost": 0
            }
          ]
        },
        {
          "label": "APR",
          "costs": [
            {
              "capacity": 0,
              "cost": 3.40000009536743
            },
            {
              "capacity": 170,
              "cost": 0
            }
          ]
        },
        {
          "label": "MAY",
          "costs": [
            {
              "capacity": 0,
              "cost": 3.40000009536743
            },
            {
              "capacity": 170,
              "cost": 0
            }
          ]
        },
        {
          "label": "JUN",
          "costs": [
            {
              "capacity": 0,
              "cost": 3.40000009536743
            },
            {
              "capacity": 170,
              "cost": 0
            }
          ]
        },
        {
          "label": "JUL",
          "costs": [
            {
              "capacity": 0,
              "cost": 3.40000009536743
            },
            {
              "capacity": 170,
              "cost": 0
            }
          ]
        },
        {
          "label": "AUG",
          "costs": [
            {
              "capacity": 0,
              "cost": 3.40000009536743
            },
            {
              "capacity": 170,
              "cost": 0
            }
          ]
        },
        {
          "label": "SEP",
          "costs": [
            {
              "capacity": 0,
              "cost": 3.40000009536743
            },
            {
              "capacity": 170,
              "cost": 0
            }
          ]
        },
        {
          "label": "OCT",
          "costs": [
            {
              "capacity": 0,
              "cost": 3.40000009536743
            },
            {
              "capacity": 170,
              "cost": 0
            }
          ]
        },
        {
          "label": "NOV",
          "costs": [
            {
              "capacity": 0,
              "cost": 3.40000009536743
            },
            {
              "capacity": 170,
              "cost": 0
            }
          ]
        },
        {
          "label": "DEC",
          "costs": [
            {
              "capacity": 0,
              "cost": 3.40000009536743
            },
            {
              "capacity": 170,
              "cost": 0
            }
          ]
        }
      ]
    },
    "constraints": {
      "constraint_type": "Bounded",
      "lower": {
        "bound_type": "Constant",
        "bound": 37
      },
      "upper": {
        "bound_type": "Constant",
        "bound": 170
      }
    }
  }
}