{
  "type": "Feature",
  "geometry": {
    "type": "Point",
    "coordinates": [
      -118.825929655088,
      34.9449713924589
    ]
  },
  "properties": {
    "prmname": "EdmonsPMP",
    "description": "Edmonston Pumping Plant",
    "type": "Pump Plant",
    "origins": [
      "D862B"
    ],
    "terminals": [
      "C103"
    ],
    "inflows": null
  }
}