{"type":"Feature",
 "geometry":{"type":"Point","coordinates":[-122.345612187351,40.4802014090923]},
 "properties":{"prmname":"HGP01",
 "description":"Hidden node for calibration of GW-1",
 "type":"Junction",
 "inflows":null,
 "sinks":null,
 "flow":{"$ref" : "flow.csv"}}}
