{
  "type": "Feature",
  "geometry": {
    "type": "Point",
    "coordinates": [
      -122.488569,
      40.445785
    ]
  },
  "properties": {
    "prmname": "HGP01",
    "description": "Hidden node for calibration of GW-1",
    "type": "Junction",
    "inflows": null,
    "sinks": null,
    "flow": {
      "$ref": "flow.csv"
    }
  }
}