{"type":"Feature",
 "geometry":{"type":"Point","coordinates":[-122.362535142639,40.4665538312452]},
 "properties":{"prmname":"HGP01",
 "description":"Hidden node for calibration of GW-1",
 "type":"Junction",
 "inflows":null,
 "sinks":null,
 "flow":{"$ref" : "flow.csv"}}}
