{"type":"Feature",
 "geometry":{"type":"Point","coordinates":[-120.234804720421,36.3234042350272]},
 "properties":{"prmname":"HXI402",
 "description":null,
 "type":"Junction",
 "inflows":null,
 "sinks":null,
 "flow":null}}
