{"type":"Feature",
 "geometry":{"type":"Point","coordinates":[-120.230231257537,36.3250280294741]},
 "properties":{"prmname":"HXI402",
 "description":null,
 "type":"Junction",
 "inflows":null,
 "sinks":null,
 "flow":null}}
