{"type":"Feature",
 "geometry":{"type":"Point","coordinates":[-120.230994818162,36.3171035382922]},
 "properties":{"prmname":"HXI402",
 "description":null,
 "type":"Junction",
 "inflows":null,
 "sinks":null,
 "flow":null}}
