{"type":"Feature",
 "geometry":{"type":"Point","coordinates":[-120.23255893221,36.3243089302727]},
 "properties":{"prmname":"HXI402",
 "description":null,
 "type":"Junction",
 "inflows":null,
 "sinks":null,
 "flow":null}}
