{"type":"Feature",
 "geometry":{"type":"Point","coordinates":[-120.106749576421,36.2021168080265]},
 "properties":{"prmname":"HXI402",
 "description":null,
 "type":"Junction",
 "inflows":null,
 "sinks":null,
 "flow":null}}
