{"type":"Feature",
 "geometry":{"type":"Point","coordinates":[-121.557166670506,39.4287013334392]},
 "properties":{"prmname":"HSU202C77",
 "description":"Hidden node on surface water conveyance channel",
 "type":"Junction",
 "inflows":null,
 "sinks":null,
 "flow":null}}
