{"type":"Feature",
 "geometry":{"type":"Point","coordinates":[-122.322156992625,37.6120482557109]},
 "properties":{"prmname":"HXI301",
 "description":null,
 "type":"Junction",
 "inflows":null,
 "sinks":null,
 "flow":{"$ref" : "flow.csv"}}}
