{"type":"Feature",
 "geometry":{"type":"Point","coordinates":[-122.326648569046,37.610269207871]},
 "properties":{"prmname":"HXI301",
 "description":null,
 "type":"Junction",
 "inflows":null,
 "sinks":null,
 "flow":{"$ref" : "flow.csv"}}}
