{"type":"Feature",
 "geometry":{"type":"Point","coordinates":[-122.324402780836,37.6111587371108]},
 "properties":{"prmname":"HXI301",
 "description":null,
 "type":"Junction",
 "inflows":null,
 "sinks":null,
 "flow":{"$ref" : "flow.csv"}}}
