{"type":"Feature",
 "geometry":{"type":"Point","coordinates":[-122.432443576421,37.7445211685162]},
 "properties":{"prmname":"HXI301",
 "description":null,
 "type":"Junction",
 "inflows":null,
 "sinks":null,
 "flow":{"$ref" : "flow.csv"}}}
