{"type":"Feature",
 "geometry":{"type":"Point","coordinates":[-122.322156992625,37.6084901174743]},
 "properties":{"prmname":"IND SFPUC",
 "description":"Includes all of DAU 43",
 "type":"Urban Demand",
 "inflows":null,
 "sinks":null,
 "flow":null}}
