{
  "type": "Feature",
  "geometry": {
    "type": "Point",
    "coordinates": [
      -119.611199466518,
      36.5298242397552
    ]
  },
  "properties": {
    "prmname": "HGP17",
    "description": "Hidden node for calibration of GW-17",
    "type": "Junction",
    "origins": [
      "GW-17"
    ],
    "terminals": [
      "T49SANGER",
      "CVPM17",
      "C55"
    ],
    "inflows": null
  }
}