{"type":"Feature",
 "geometry":{"type":"Point","coordinates":[-122.098831500502,38.3149985455252]},
 "properties":{"prmname":"HXI205",
 "description":null,
 "type":"Junction",
 "inflows":null,
 "sinks":null,
 "flow":{"$ref" : "flow.csv"}}}
