{"type":"Feature",
 "geometry":{"type":"Point","coordinates":[-122.085077079746,38.3458555448567]},
 "properties":{"prmname":"HXI205",
 "description":null,
 "type":"Junction",
 "inflows":null,
 "sinks":null,
 "flow":{"$ref" : "flow.csv"}}}
