{"type":"Feature",
 "geometry":{"type":"Point","coordinates":[-120.496582576421,37.2861434967756]},
 "properties":{"prmname":"EXT_CVPM15",
 "description":"100% of DAU 238, 235, 237, 241, & 246, exterior",
 "type":"Urban Demand",
 "inflows":null,
 "sinks":null,
 "flow":null}}
