{"type":"Feature",
 "geometry":{"type":"Point","coordinates":[-120.994729737195,38.213982425699]},
 "properties":{"prmname":"INT CVPM08",
 "description":"100% of DAU 180, interior",
 "type":"Urban Demand",
 "inflows":null,
 "sinks":null,
 "flow":null}}
