{
  "type": "Feature",
  "geometry": {
    "type": "Point",
    "coordinates": [
      -121.065955423579,
      38.418565970888
    ]
  },
  "properties": {
    "prmname": "INT_CVPM08",
    "description": "100% of DAU 180, interior",
    "type": "Urban Demand",
    "inflows": null,
    "sinks": null,
    "flow": {
      "$ref": "flow.csv"
    }
  }
}