{"type":"Feature",
 "geometry":{"type":"Point","coordinates":[-121.624061,37.7979270000001]},
 "properties":{"prmname":"PMP_Banks",
 "description":"Banks Pumping Plant",
 "type":"Pump Plant",
 "inflows":null,
 "sinks":null,
 "flow":null}}
