{"type":"Feature",
 "geometry":{"type":"Point","coordinates":[-122.090276,37.9780153989662]},
 "properties":{"prmname":"WWP208",
 "description":"CCWD OUT",
 "type":"Water Treatment",
 "inflows":null,
 "sinks":[{"default" : {"description" : "Contra Costa", "costs" : {"type":"Constant",
 "cost":0}, "bounds" : [{"type":"NOB"}], "flow" : {"$ref" : "./sinks/default/flow.csv"}}}],
 "flow":{"$ref" : "flow.csv"}}}
