{"type":"Feature",
 "geometry":{"type":"Point","coordinates":[-114.528544635369,33.7246868760218]},
 "properties":{"prmname":"WTP508",
 "description":null,
 "type":"Water Treatment",
 "inflows":null,
 "sinks":null,
 "flow":null}}
