{"type":"Feature",
 "geometry":{"type":"Point","coordinates":[-119.561049462997,35.4850946372246]},
 "properties":{"prmname":"CVPM19BG",
 "description":"",
 "type":"Agricultural Demand",
 "costs":null,
 "bounds":null,
 "sinks":null}}
