{"type":"Feature",
 "geometry":{"type":"Point","coordinates":[-121.022053113809,38.2249175915377]},
 "properties":{"prmname":"SR-CMN",
 "description":"Camanche Res",
 "type":"Surface Storage",
 "initialstorage":200,
 "endingstorage":235,
 "areacapfactor":0.005604,
 "inflows":null,
 "el_ar_cap":{"$ref":"elevation_area_capacity.csv"},
 "costs":{ "type":"Monthly Variable","costs":{"JAN":{"$ref":"cost_JAN.csv"},"FEB":{"$ref":"cost_FEB.csv"},"MAR":{"$ref":"cost_MAR.csv"},"APR":{"$ref":"cost_APR.csv"},"MAY":{"$ref":"cost_MAY.csv"},"JUN":{"$ref":"cost_JUN.csv"},"JUL":{"$ref":"cost_JUL.csv"},"AUG":{"$ref":"cost_AUG.csv"},"SEP":{"$ref":"cost_SEP.csv"},"OCT":{"$ref":"cost_OCT.csv"},"NOV":{"$ref":"cost_NOV.csv"},"DEC":{"$ref":"cost_DEC.csv"}}},
 "bounds":[{"type":"LBC","bound":4},{"type":"UBT","bound": {"$ref":"./UBT.csv"}}],
 "sinks":null}}
