{"type":"Feature",
 "geometry":{"type":"Point","coordinates":[-121.935121594619,39.2846964013788]},
 "properties":{"prmname":"HSU104D30",
 "description":"Hidden node on surface water conveyance channel",
 "type":"Junction",
 "inflows":null,
 "sinks":null}}
