{"type":"Feature",
 "geometry":{"type":"Point","coordinates":[-121.788505457248,39.1998786011324]},
 "properties":{"prmname":"HSU104D30",
 "description":"Hidden node on surface water conveyance channel",
 "type":"Junction",
 "inflows":null,
 "sinks":null,
 "flow":null}}
