{"type":"Feature",
 "geometry":{"type":"Point","coordinates":[-121.925627126406,39.3545520354543]},
 "properties":{"prmname":"HSU104D30",
 "description":"Hidden node on surface water conveyance channel",
 "type":"Junction",
 "inflows":null,
 "sinks":null,
 "flow":null}}
