{"type":"Feature",
 "geometry":{"type":"Point","coordinates":[-119.361326242487,36.0316808934384]},
 "properties":{"prmname":"HSUR402",
 "description":"Hidden node for conveyance loss for deliveries to Pixley NWR",
 "type":"Junction",
 "inflows":null,
 "sinks":null,
 "flow":null}}
