{
  "type": "Feature",
  "geometry": {
    "type": "Point",
    "coordinates": [
      -119.325802,
      36.071045
    ]
  },
  "properties": {
    "prmname": "HSUR402",
    "description": "Hidden node for conveyance loss for deliveries to Pixley NWR",
    "type": "Junction",
    "inflows": null,
    "sinks": null,
    "flow": {
      "$ref": "flow.csv"
    }
  }
}