{"type":"Feature",
 "geometry":{"type":"Point","coordinates":[-119.296949689504,36.1341461463674]},
 "properties":{"prmname":"HSUR402",
 "description":"Hidden node for conveyance loss for deliveries to Pixley NWR",
 "type":"Junction",
 "inflows":null,
 "sinks":null,
 "flow":null}}
