{
  "type": "Feature",
  "geometry": {
    "type": "Point",
    "coordinates": [
      -117.569211,
      34.626077
    ]
  },
  "properties": {
    "prmname": "HGRMJ",
    "description": null,
    "type": "Junction",
    "inflows": null,
    "sinks": null,
    "flow": {
      "$ref": "flow.csv"
    }
  }
}