{"type":"Feature",
 "geometry":{"type":"Point","coordinates":[-116.480233022545,34.6811094954677]},
 "properties":{"prmname":"HGRMJ",
 "description":null,
 "type":"Junction",
 "inflows":null,
 "sinks":null,
 "flow":null}}
