{"type":"Feature",
 "geometry":{"type":"Point","coordinates":[-116.607909,34.8506579999999]},
 "properties":{"prmname":"HGRMJ",
 "description":null,
 "type":"Junction",
 "inflows":null,
 "sinks":null,
 "flow":null}}
