{"type":"Feature",
 "geometry":{"type":"Point","coordinates":[-115.711344452877,33.2413508711365]},
 "properties":{"prmname":"HNP510",
 "description":null,
 "type":"Junction",
 "inflows":null,
 "sinks":null,
 "flow":null}}
