{"type":"Feature",
 "geometry":{"type":"Point","coordinates":[-119.943413,35.83651]},
 "properties":{"prmname":"PMP_Badger",
 "description":"Badger Hill Pumping Plant",
 "type":"Pump Plant",
 "inflows":null,
 "sinks":null,
 "flow":null}}
