{"type":"Feature",
 "geometry":{"type":"Point","coordinates":[-119.943412887195,35.8365097708612]},
 "properties":{"prmname":"PMP-Badger",
 "description":"Badger Hill Pumping Plant",
 "type":"Pump Plant",
 "inflows":null,
 "sinks":null,
 "flow":null}}
