{
  "type": "Feature",
  "geometry": {
    "type": "Point",
    "coordinates": [
      -121.18422603999,
      38.5108469206665
    ]
  },
  "properties": {
    "prmname": "HGP8",
    "description": "Hidden node for calibration of GW-8",
    "type": "Junction",
    "origins": [
      "GW-8"
    ],
    "terminals": [
      "T4SAC",
      "CVPM8",
      "C36",
      "T43GALT",
      "T26STOC"
    ],
    "inflows": null
  }
}