{"type":"Feature",
 "geometry":{"type":"Point","coordinates":[-115.461648844132,33.0140331139993]},
 "properties":{"prmname":"EXT El Cen",
 "description":"DAU 353-357 Exterior Res/Landscape demand",
 "type":"Urban Demand",
 "inflows":null,
 "sinks":null,
 "flow":null}}
