{"type":"Feature",
 "geometry":{"type":"Point","coordinates":[-115.463894632343,33.008383402508]},
 "properties":{"prmname":"EXT_El_Cen",
 "description":"DAU 353-357 Exterior Res/Landscape demand",
 "type":"Urban Demand",
 "inflows":null,
 "sinks":null,
 "flow":null}}
