{"type":"Feature",
 "geometry":{"type":"Point","coordinates":[-115.463894632342,33.0159162707306]},
 "properties":{"prmname":"EXT El Cen",
 "description":"DAU 353-357 Exterior Res/Landscape demand",
 "type":"Urban Demand",
 "inflows":null,
 "sinks":null,
 "flow":null}}
