{"type":"Feature",
 "geometry":{"type":"Point","coordinates":[-115.566139576421,32.7825238690415]},
 "properties":{"prmname":"EXT_El_Cen",
 "description":"DAU 353-357 Exterior Res/Landscape demand",
 "type":"Urban Demand",
 "inflows":null,
 "sinks":null,
 "flow":null}}
