{"type":"Feature",
 "geometry":{"type":"Point","coordinates":[-114.468429889868,32.8715614055908]},
 "properties":{"prmname":"HSU512C143",
 "description":"Hidden Ag Water Supply node for Bard WD",
 "type":"Junction",
 "inflows":null,
 "sinks":null,
 "flow":null}}
