{"type":"Feature",
 "geometry":{"type":"Point","coordinates":[-114.538442847159,32.7921994798158]},
 "properties":{"prmname":"HSU512C143",
 "description":"Hidden Ag Water Supply node for Bard WD",
 "type":"Junction",
 "inflows":null,
 "sinks":null,
 "flow":null}}
