{"type":"Feature",
 "geometry":{"type":"Point","coordinates":[-114.463938313448,32.8706182937588]},
 "properties":{"prmname":"HSU512C143",
 "description":"Hidden Ag Water Supply node for Bard WD",
 "type":"Junction",
 "inflows":null,
 "sinks":null,
 "flow":null}}
