{"type":"Feature",
 "geometry":{"type":"Point","coordinates":[-122.050181467941,38.4240202324968]},
 "properties":{"prmname":"INT CVPM06",
 "description":"100% of DAU 162, 9% of DAU 191, 40 & 41, interior",
 "type":"Urban Demand",
 "inflows":null,
 "sinks":null,
 "flow":null}}
