{"type":"Feature",
 "geometry":{"type":"Point","coordinates":[-122.200322576421,39.2754351044476]},
 "properties":{"prmname":"EXT_YUBA",
 "description":"Exterior demand for Yuba City et al. Includes Yuba City and parts of Butte Co. but not Plumas Co. surface water demand (DAU 159, 168)",
 "type":"Urban Demand",
 "inflows":null,
 "sinks":null,
 "flow":null}}
