{
  "type": "Feature",
  "geometry": {
    "type": "Point",
    "coordinates": [
      -120.815047075154,
      38.1549199429767
    ]
  },
  "properties": {
    "prmname": "SR-NHL",
    "description": "New Hogan Lake",
    "type": "Surface Storage",
    "origins": [
      "CN2"
    ],
    "terminals": [
      "C40"
    ],
    "initialstorage": 159,
    "endingstorage": 92,
    "areacapfactor": 0.011182,
    "inflows": null,
    "el_ar_cap": {
      "$ref": "el_ar_cap.csv"
    },
    "costs": {
      "type": "Monthly Variable",
      "costs": [
        {
          "label": "JAN",
          "costs": [
            {
              "capacity": 0,
              "cost": 3.29999995231628
            },
            {
              "capacity": 165,
              "cost": 0
            }
          ]
        },
        {
          "label": "FEB",
          "costs": [
            {
              "capacity": 0,
              "cost": 3.75999999046326
            },
            {
              "capacity": 188,
              "cost": 0
            }
          ]
        },
        {
          "label": "MAR",
          "costs": [
            {
              "capacity": 0,
              "cost": 4.21999979019165
            },
            {
              "capacity": 211,
              "cost": 0
            }
          ]
        },
        {
          "label": "APR",
          "costs": [
            {
              "capacity": 0,
              "cost": 5.40000009536743
            },
            {
              "capacity": 270,
              "cost": 0
            }
          ]
        },
        {
          "label": "MAY",
          "costs": [
            {
              "capacity": 0,
              "cost": 6.30000019073486
            },
            {
              "capacity": 315,
              "cost": 0
            }
          ]
        },
        {
          "label": "JUN",
          "costs": [
            {
              "capacity": 0,
              "cost": 6.34000015258789
            },
            {
              "capacity": 317,
              "cost": 0
            }
          ]
        },
        {
          "label": "JUL",
          "costs": [
            {
              "capacity": 0,
              "cost": 6.34000015258789
            },
            {
              "capacity": 317,
              "cost": 0
            }
          ]
        },
        {
          "label": "AUG",
          "costs": [
            {
              "capacity": 0,
              "cost": 6.34000015258789
            },
            {
              "capacity": 317,
              "cost": 0
            }
          ]
        },
        {
          "label": "SEP",
          "costs": [
            {
              "capacity": 0,
              "cost": 6.34000015258789
            },
            {
              "capacity": 317,
              "cost": 0
            }
          ]
        },
        {
          "label": "OCT",
          "costs": [
            {
              "capacity": 0,
              "cost": 5.48000001907349
            },
            {
              "capacity": 274,
              "cost": 0
            }
          ]
        },
        {
          "label": "NOV",
          "costs": [
            {
              "capacity": 0,
              "cost": 3.8199999332428
            },
            {
              "capacity": 191,
              "cost": 0
            }
          ]
        },
        {
          "label": "DEC",
          "costs": [
            {
              "capacity": 0,
              "cost": 3.03999996185303
            },
            {
              "capacity": 152,
              "cost": 0
            }
          ]
        }
      ]
    },
    "constraints": {
      "constraint_type": "Bounded",
      "lower": {
        "bound_type": "Constant",
        "bound": 17.5
      },
      "upper": {
        "$ref": "constraints_upper_date.csv"
      }
    }
  }
}