{
  "type": "Feature",
  "geometry": {
    "type": "Point",
    "coordinates": [
      -120.815047075154,
      38.1549199429767
    ]
  },
  "properties": {
    "prmname": "SR-NHL",
    "description": "New Hogan Lake",
    "type": "Surface Storage",
    "origins": [
      "CN2"
    ],
    "terminals": [
      "C40"
    ],
    "initialstorage": 159,
    "endingstorage": 92,
    "areacapfactor": 0.011182,
    "inflows": null,
    "el_ar_cap": [
      {
        "elevation": 589.180969238281,
        "area": 0.795040965080261,
        "capacity": 17.5
      },
      {
        "elevation": 618.866455078125,
        "area": 1.51586627960205,
        "capacity": 51.6699981689453
      },
      {
        "elevation": 637.773193359375,
        "area": 2.03847503662109,
        "capacity": 85.8300018310547
      },
      {
        "elevation": 652.659729003906,
        "area": 2.47510719299316,
        "capacity": 120
      },
      {
        "elevation": 665.317321777344,
        "area": 2.85990023612976,
        "capacity": 154.169998168945
      },
      {
        "elevation": 676.523315429688,
        "area": 3.20886301994324,
        "capacity": 188.330001831055
      },
      {
        "elevation": 686.702331542969,
        "area": 3.53132271766663,
        "capacity": 222.5
      },
      {
        "elevation": 696.104187011719,
        "area": 3.83294773101807,
        "capacity": 256.670013427734
      },
      {
        "elevation": 704.892700195312,
        "area": 4.11758995056152,
        "capacity": 290.829986572266
      },
      {
        "elevation": 713.188842773438,
        "area": 4.38823938369751,
        "capacity": 325
      }
    ],
    "costs": {
      "type": "Monthly Variable",
      "costs": {
        "$ref": "costs_costs.json"
      }
    },
    "constraints": {
      "constraint_type": "Bounded",
      "lower": {
        "bound_type": "Constant",
        "bound": 17.5
      },
      "upper": {
        "bound_type": "TimeSeries",
        "date": {
          "$ref": "constraints_upper_date.json"
        },
        "bound": {
          "$ref": "constraints_upper_bound.json"
        }
      }
    }
  }
}