{"type":"Feature",
 "geometry":{"type":"Point","coordinates":[-119.5602224106,35.4772212567289]},
 "properties":{"prmname":"Ext CVPM19",
 "description":"100% of DAU 255, 259 & 260, exterior",
 "type":"Urban Demand",
 "inflows":null,
 "sinks":null,
 "flow":null}}
