{"type":"Feature",
 "geometry":{"type":"Point","coordinates":[-119.56285146559,35.462331284518]},
 "properties":{"prmname":"Ext_CVPM19",
 "description":"100% of DAU 255, 259 & 260, exterior",
 "type":"Urban Demand",
 "inflows":null,
 "sinks":null,
 "flow":null}}
