{"type":"Feature",
 "geometry":{"type":"Point","coordinates":[-119.562468198811,35.4790500852928]},
 "properties":{"prmname":"Ext CVPM19",
 "description":"100% of DAU 255, 259 & 260, exterior",
 "type":"Urban Demand",
 "inflows":null,
 "sinks":null,
 "flow":null}}
