{"type":"Feature",
 "geometry":{"type":"Point","coordinates":[-119.313373023508,36.6271664682844]},
 "properties":{"prmname":"CVPM17G",
 "description":"junction node for CVPM 17",
 "type":"Agricultural Demand",
 "inflows":null,
 "sinks":null,
 "flow":null}}
