{"type":"Feature",
 "geometry":{"type":"Point","coordinates":[-119.315618576421,36.6325736913264]},
 "properties":{"prmname":"CVPM17G",
 "description":"junction node for CVPM 17",
 "type":"Agricultural Demand",
 "inflows":null,
 "sinks":null,
 "flow":null}}
