{"type":"Feature",
 "geometry":{"type":"Point","coordinates":[-119.326261576421,36.6119307259569]},
 "properties":{"prmname":"CVPM17G",
 "description":"junction node for CVPM 17",
 "type":"Agricultural Demand",
 "inflows":null,
 "sinks":null,
 "flow":null}}
