{"type":"Feature",
 "geometry":{"type":"Point","coordinates":[-116.160780358716,34.6775518398412]},
 "properties":{"prmname":"HNP505",
 "description":null,
 "type":"Junction",
 "inflows":null,
 "sinks":null,
 "flow":null}}
