{"type":"Feature",
 "geometry":{"type":"Point","coordinates":[-116.149381668619,34.675084407758]},
 "properties":{"prmname":"HNP505",
 "description":null,
 "type":"Junction",
 "inflows":null,
 "sinks":null,
 "flow":null}}
