{
  "type": "Feature",
  "geometry": {
    "type": "Point",
    "coordinates": [
      -121.624061446168,
      37.7979274027524
    ]
  },
  "properties": {
    "prmname": "Banks PMP",
    "description": "Banks Pumping Plant",
    "type": "Pump Plant",
    "origins": [
      "D59"
    ],
    "terminals": [
      "D801"
    ],
    "inflows": null
  }
}