{
  "type": "Feature",
  "geometry": {
    "type": "Point",
    "coordinates": [
      -120.80715699851,
      37.5718751854015
    ]
  },
  "properties": {
    "prmname": "HGP11",
    "description": "Hidden node for calibration of GW-11",
    "type": "Junction",
    "origins": [
      "GW-11"
    ],
    "terminals": [
      "C172",
      "T45MODEST",
      "CVPM11"
    ],
    "inflows": null
  }
}