{
  "type": "Feature",
  "geometry": {
    "type": "Point",
    "coordinates": [
      -120.706070535435,
      35.7074505158318
    ]
  },
  "properties": {
    "prmname": "Sink R3",
    "description": "",
    "type": "Sink",
    "origins": [
      "C45",
      "C66",
      "C63",
      "C100",
      "C60",
      "C55",
      "C50",
      "C90",
      "C91",
      "C46",
      "C172",
      "C84"
    ],
    "terminals": null,
    "inflows": null
  }
}