{
  "type": "Feature",
  "geometry": {
    "type": "Point",
    "coordinates": [
      -117.862728451475,
      34.0343816478517
    ]
  },
  "properties": {
    "prmname": "T10CMWD",
    "description": "Central MWD OUT",
    "type": "Water Treatment",
    "origins": [
      "IRes CMWD",
      "Ind: CMWD"
    ],
    "terminals": [
      "Sink G37",
      "T5CMWD",
      "HWWT10"
    ],
    "inflows": null
  }
}