{
  "type": "Feature",
  "geometry": {
    "type": "Point",
    "coordinates": [
      -119.272875113907,
      36.0211436935293
    ]
  },
  "properties": {
    "prmname": "HAR18",
    "description": "Artificial recharge node",
    "type": "Junction",
    "origins": [
      "C688",
      "C58",
      "C56"
    ],
    "terminals": [
      "GW-18"
    ],
    "inflows": null
  }
}