{"type":"Feature",
 "geometry":{"type":"Point","coordinates":[-119.442091,36.5907976448333]},
 "properties":{"prmname":"WWP403",
 "description":"Sanger CVPM17 Urban OUT",
 "type":"Water Treatment",
 "inflows":null,
 "sinks":null,
 "flow":{"$ref" : "flow.csv"}}}
