{"type":"Feature",
 "geometry":{"type":"Point","coordinates":[-119.503073985295,36.5792993461957]},
 "properties":{"prmname":"WWP403",
 "description":"Sanger CVPM17 Urban OUT",
 "type":"Water Treatment",
 "inflows":null,
 "sinks":null,
 "flow":null}}
