{
  "type": "Feature",
  "geometry": {
    "type": "Point",
    "coordinates": [
      -121.075970028372,
      37.0683748019292
    ]
  },
  "properties": {
    "prmname": "GianelPWP",
    "description": "Gianelli Power Plant",
    "type": "Power Plant",
    "origins": [
      "SR-12"
    ],
    "terminals": [
      "D816"
    ],
    "inflows": null
  }
}