{"type":"Feature",
 "geometry":{"type":"Point","coordinates":[-118.061053436259,35.0834439804842]},
 "properties":{"prmname":"WTP502",
 "description":"",
 "type":"Water Treatment",
 "inflows":null,
 "sinks":null}}
