{"type":"Feature",
 "geometry":{"type":"Point","coordinates":[-117.879679790433,35.3483250783625]},
 "properties":{"prmname":"WTP502",
 "description":null,
 "type":"Water Treatment",
 "inflows":null,
 "sinks":null,
 "flow":null}}
