{"type":"Feature",
 "geometry":{"type":"Point","coordinates":[-117.607696534321,35.5013546971249]},
 "properties":{"prmname":"WTP502",
 "description":null,
 "type":"Water Treatment",
 "inflows":null,
 "sinks":null,
 "flow":null}}
