{"type":"Feature",
 "geometry":{"type":"Point","coordinates":[-122.173720601269,37.7664058165952]},
 "properties":{"prmname":"ERES EBMUD",
 "description":"EBMUD exterior urban demand Parts of DAU 46 & 47",
 "type":"Urban Demand",
 "inflows":null,
 "sinks":{"default":{"description":null,"costs":{"type":"Constant",
 "cost":0},"bounds":[{"type":"NOB"}]}},
 "flow":null}}
