{"type":"Feature",
 "geometry":{"type":"Point","coordinates":[-122.169229024848,37.7646304677221]},
 "properties":{"prmname":"ERES EBMUD",
 "description":"EBMUD exterior urban demand Parts of DAU 46 & 47",
 "type":"Urban Demand",
 "inflows":null,
 "sinks":{"default":{"description":null,"costs":{"type":"Constant",
 "cost":0},"bounds":[{"type":"NOB"}]}},
 "flow":null}}
