{"type":"Feature",
 "geometry":{"type":"Point","coordinates":[-117.495973778899,34.5840318345504]},
 "properties":{"prmname":"HARMJ",
 "description":"Hidden node for artificial groundwater recharge",
 "type":"Junction",
 "inflows":null,
 "sinks":null,
 "flow":null}}
