{"type":"Feature",
 "geometry":{"type":"Point","coordinates":[-117.102984,34.603329]},
 "properties":{"prmname":"HARMJ",
 "description":"Hidden node for artificial groundwater recharge",
 "type":"Junction",
 "inflows":null,
 "sinks":null,
 "flow":null}}
