{"type":"Feature",
 "geometry":{"type":"Point","coordinates":[-116.161917451223,34.691849110476]},
 "properties":{"prmname":"HARMJ",
 "description":"Hidden node for artificial groundwater recharge",
 "type":"Junction",
 "inflows":null,
 "sinks":null,
 "flow":null}}
