{"type":"Feature",
 "geometry":{"type":"Point","coordinates":[-121.927692820842,39.0948111902416]},
 "properties":{"prmname":"HGR04",
 "description":"Hidden node for calibration of GW-4",
 "type":"Junction",
 "inflows":null,
 "sinks":null,
 "flow":null}}
