{
  "type": "Feature",
  "geometry": {
    "type": "Point",
    "coordinates": [
      -119.746071576421,
      36.5417454472391
    ]
  },
  "properties": {
    "prmname": "CVPM16G",
    "description": "junction node for CVPM 16",
    "type": "Agricultural Demand",
    "inflows": null,
    "sinks": null,
    "flow": {
      "$ref": "flow.csv"
    }
  }
}