{"type":"Feature",
 "geometry":{"type":"Point","coordinates":[-119.824475953505,36.7546549578863]},
 "properties":{"prmname":"CVPM16G",
 "description":"junction node for CVPM 16",
 "type":"Agricultural Demand",
 "inflows":null,
 "sinks":null,
 "flow":null}}
