{
  "type": "Feature",
  "geometry": {
    "type": "Point",
    "coordinates": [
      -122.187346354897,
      39.2606714671897
    ]
  },
  "properties": {
    "prmname": "INT CVPM3",
    "description": "100% of DAU 163, interior",
    "type": "Urban Demand",
    "origins": [
      "HGP3"
    ],
    "terminals": [
      "HGU3"
    ],
    "inflows": null
  }
}