{"type":"Feature",
 "geometry":{"type":"Point","coordinates":[-120.887911800096,38.0989530202401]},
 "properties":{"prmname":"CVPM08S",
 "description":"junction node for CVPM 8",
 "type":"Agricultural Demand",
 "inflows":null,
 "sinks":null,
 "flow":null}}
