{"type":"Feature",
 "geometry":{"type":"Point","coordinates":[-121.174711423579,38.1921109668452]},
 "properties":{"prmname":"CVPM08S",
 "description":"junction node for CVPM 8",
 "type":"Agricultural Demand",
 "inflows":null,
 "sinks":null,
 "flow":null}}
