{"type":"Feature",
 "geometry":{"type":"Point","coordinates":[-120.885666011885,38.1183908960502]},
 "properties":{"prmname":"CVPM08S",
 "description":"junction node for CVPM 8",
 "type":"Agricultural Demand",
 "inflows":null,
 "sinks":null,
 "flow":null}}
