{"type":"Feature",
 "geometry":{"type":"Point","coordinates":[-121.055239423579,38.0297361105579]},
 "properties":{"prmname":"CVPM08S",
 "description":"junction node for CVPM 8",
 "type":"Agricultural Demand",
 "inflows":null,
 "sinks":null,
 "flow":null}}
