{"type":"Feature",
 "geometry":{"type":"Point","coordinates":[-120.880686613862,37.1146243326682]},
 "properties":{"prmname":"EXT CVPM10",
 "description":"100% of DAU 216, exterior",
 "type":"Urban Demand",
 "inflows":null,
 "sinks":null,
 "flow":null}}
