{
  "type": "Feature",
  "geometry": {
    "type": "Point",
    "coordinates": [
      -120.849275576421,
      37.0700572600907
    ]
  },
  "properties": {
    "prmname": "EXT_CVPM10",
    "description": "100% of DAU 216, exterior",
    "type": "Urban Demand",
    "inflows": null,
    "sinks": null,
    "flow": {
      "$ref": "flow.csv"
    }
  }
}