{"type":"Feature",
 "geometry":{"type":"Point","coordinates":[-120.854975626501,37.1447094016813]},
 "properties":{"prmname":"EXT CVPM10",
 "description":"100% of DAU 216, exterior",
 "type":"Urban Demand",
 "inflows":null,
 "sinks":null,
 "flow":null}}
