{"type":"Feature",
 "geometry":{"type":"Point","coordinates":[-120.848932576421,37.0689612082971]},
 "properties":{"prmname":"EXT_CVPM10",
 "description":"100% of DAU 216, exterior",
 "type":"Urban Demand",
 "inflows":null,
 "sinks":null,
 "flow":null}}
