{"type":"Feature",
 "geometry":{"type":"Point","coordinates":[-121.432125847159,39.3046838993709]},
 "properties":{"prmname":"HSU202C80",
 "description":"Hidden node on surface water conveyance channel",
 "type":"Junction",
 "inflows":null,
 "sinks":null,
 "flow":{"$ref" : "flow.csv"}}}
