{"type":"Feature",
 "geometry":{"type":"Point","coordinates":[-114.938222182378,33.9418206065756]},
 "properties":{"prmname":"INT Blythe",
 "description":"DAU 333-347 Ind/Interior Res/Comm",
 "type":"Urban Demand",
 "inflows":null,
 "sinks":null,
 "flow":null}}
