{"type":"Feature",
 "geometry":{"type":"Point","coordinates":[-114.940467970588,33.9436837032305]},
 "properties":{"prmname":"INT Blythe",
 "description":"DAU 333-347 Ind/Interior Res/Comm",
 "type":"Urban Demand",
 "inflows":null,
 "sinks":null,
 "flow":null}}
