{"type":"Feature",
 "geometry":{"type":"Point","coordinates":[-122.36702671906,40.4597192360695]},
 "properties":{"prmname":"HNP101",
 "description":null,
 "type":"Junction",
 "inflows":null,
 "sinks":null,
 "flow":null}}
