{"type":"Feature",
 "geometry":{"type":"Point","coordinates":[-122.36478093085,40.4631366205827]},
 "properties":{"prmname":"HNP101",
 "description":null,
 "type":"Junction",
 "inflows":null,
 "sinks":null,
 "flow":null}}
