{"type":"Feature",
 "geometry":{"type":"Point","coordinates":[-122.362535142639,40.4665538312452]},
 "properties":{"prmname":"HNP101",
 "description":null,
 "type":"Junction",
 "inflows":null,
 "sinks":null,
 "flow":null}}
