{"type":"Feature",
 "geometry":{"type":"Point","coordinates":[-121.070447,38.4150467703479]},
 "properties":{"prmname":"WWP207",
 "description":"Wastewater treatment node for all of CVPM 8, representing the town of Galt",
 "type":"Water Treatment",
 "inflows":null,
 "sinks":null,
 "flow":{"$ref" : "flow.csv"}}}
