{"type":"Feature",
 "geometry":{"type":"Point","coordinates":[-120.996976,38.2086887122008]},
 "properties":{"prmname":"WWP207",
 "description":"Wastewater treatment node for all of CVPM 8, representing the town of Galt",
 "type":"Water Treatment",
 "inflows":null,
 "sinks":null,
 "flow":{"$ref" : "flow.csv"}}}
