{
  "type": "Feature",
  "geometry": {
    "type": "Point",
    "coordinates": [
      -117.688204369656,
      33.7992227312183
    ]
  },
  "properties": {
    "prmname": "Sink G34",
    "description": "CASTAIC LAKE WA outflow",
    "type": "Sink",
    "origins": null,
    "terminals": null,
    "inflows": null
  }
}