{"type":"Feature",
 "geometry":{"type":"Point","coordinates":[-118.018588587374,34.1974126511122]},
 "properties":{"prmname":"WTP511",
 "description":null,
 "type":"Water Treatment",
 "inflows":null,
 "sinks":null,
 "flow":null}}
