{"type":"Feature",
 "geometry":{"type":"Point","coordinates":[-121.993700561921,38.4522328348174]},
 "properties":{"prmname":"WWP203",
 "description":"",
 "type":"Water Treatment",
 "inflows":null,
 "sinks":null}}
