{"type":"Feature",
 "geometry":{"type":"Point","coordinates":[-120.671845,35.2735444472212]},
 "properties":{"prmname":"WWP406",
 "description":"wastewater return flow node for SB-SLO",
 "type":"Junction",
 "inflows":null,
 "sinks":[{"default" : {"description" : "SB-SLO outflow to ocean", "costs" : {"type":"Constant",
 "cost":0}, "bounds" : [{"type":"NOB"}], "flow" : {"$ref" : "./sinks/default/flow.csv"}}}],
 "flow":{"$ref" : "flow.csv"}}}
