{
  "type": "Feature",
  "geometry": {
    "type": "Point",
    "coordinates": [
      -121.140082372049,
      38.588858752234
    ]
  },
  "properties": {
    "prmname": "HWWT13",
    "description": "Hidden node for wastewater recycling for Greater Sacramento",
    "type": "Junction",
    "origins": [
      "T13SAC"
    ],
    "terminals": [
      "T4SAC"
    ],
    "inflows": null
  }
}