{
  "type": "Feature",
  "geometry": {
    "type": "Point",
    "coordinates": [
      -122.094767576421,
      37.9780153989662
    ]
  },
  "properties": {
    "prmname": "HNP208",
    "description": null,
    "type": "Junction",
    "inflows": null,
    "sinks": null,
    "flow": {
      "$ref": "flow.csv"
    }
  }
}