{"type":"Feature",
 "geometry":{"type":"Point","coordinates":[-122.117083576421,38.0080482975854]},
 "properties":{"prmname":"HNP208",
 "description":null,
 "type":"Junction",
 "inflows":null,
 "sinks":null,
 "flow":null}}
