{
  "type": "Feature",
  "geometry": {
    "type": "Point",
    "coordinates": [
      -121.536484840759,
      38.0887046359413
    ]
  },
  "properties": {
    "prmname": "GW-9",
    "description": "Central Valley groundwater basin",
    "type": "Groundwater Storage",
    "origins": [
      "CVPM9",
      "HGU9"
    ],
    "terminals": [
      "HGP9"
    ],
    "initialstorage": 139472,
    "endingstorage": 139843,
    "inflows": [
      {
        "name": "Groundwater inflow GW-9 based on C2VSIM Historical Run356",
        "date": {
          "$ref": "inflows_0_date.json"
        },
        "inflow": {
          "$ref": "inflows_0_inflow.json"
        }
      }
    ],
    "costs": {
      "type": "Constant",
      "cost": 0
    },
    "constraints": {
      "constraint_type": "Bounded",
      "lower": {
        "bound_type": "None"
      },
      "upper": {
        "bound_type": "None"
      }
    }
  }
}