{"type":"Feature",
 "geometry":{"type":"Point","coordinates":[-116.853102847159,32.8780589544276]},
 "properties":{"prmname":"HSU511N8",
 "description":null,
 "type":"Junction",
 "inflows":null,
 "sinks":null,
 "flow":null}}
