{"type":"Feature",
 "geometry":{"type":"Point","coordinates":[-116.837896136737,33.0464434853011]},
 "properties":{"prmname":"HSU511N8",
 "description":null,
 "type":"Junction",
 "inflows":null,
 "sinks":null,
 "flow":null}}
