{"type":"Feature",
 "geometry":{"type":"Point","coordinates":[-116.833404560316,33.0455022380791]},
 "properties":{"prmname":"HSU511N8",
 "description":null,
 "type":"Junction",
 "inflows":null,
 "sinks":null,
 "flow":null}}
