{"type":"Feature",
 "geometry":{"type":"Point","coordinates":[-116.771753530158,33.0531061540948]},
 "properties":{"prmname":"HSU511N8",
 "description":null,
 "type":"Junction",
 "inflows":null,
 "sinks":null,
 "flow":null}}
