{"type":"Feature",
 "geometry":{"type":"Point","coordinates":[-122.121206570792,39.296879063696]},
 "properties":{"prmname":"CVPM03AS",
 "description":"junction node for CVPM 3",
 "type":"Agricultural Demand",
 "inflows":null,
 "sinks":null,
 "flow":null}}
