{"type":"Feature",
 "geometry":{"type":"Point","coordinates":[-122.123452359002,39.3020927456398]},
 "properties":{"prmname":"CVPM03AS",
 "description":"junction node for CVPM 3",
 "type":"Agricultural Demand",
 "inflows":null,
 "sinks":null,
 "flow":null}}
