{"type":"Feature",
 "geometry":{"type":"Point","coordinates":[-118.789214,34.686966]},
 "properties":{"prmname":"PWP_Warne",
 "description":"West Branch SWP Power Plant",
 "type":"Power Plant",
 "inflows":null,
 "sinks":null,
 "flow":null}}
