{
  "type": "Feature",
  "geometry": {
    "type": "Point",
    "coordinates": [
      -119.620335315972,
      35.5061994937699
    ]
  },
  "properties": {
    "prmname": "GW-19",
    "description": "Central Valley groundwater basin",
    "type": "Groundwater Storage",
    "origins": [
      "CVPM19",
      "HGU19",
      "HAR19"
    ],
    "terminals": [
      "HGP19"
    ],
    "initialstorage": 141750,
    "endingstorage": 128223,
    "inflows": [
      {
        "name": "Groundwater inflow GW-19 C2VSIM Historical Run 1980-2000 ",
        "date": {
          "$ref": "inflows_0_date.json"
        },
        "inflow": {
          "$ref": "inflows_0_inflow.json"
        }
      }
    ],
    "costs": {
      "type": "Constant",
      "cost": 0
    },
    "constraints": {
      "constraint_type": "Bounded",
      "lower": {
        "bound_type": "None"
      },
      "upper": {
        "bound_type": "None"
      }
    }
  }
}