{"type":"Feature",
 "geometry":{"type":"Point","coordinates":[-121.738521734328,37.346014931244]},
 "properties":{"prmname":"HXI304",
 "description":null,
 "type":"Junction",
 "inflows":null,
 "sinks":null,
 "flow":{"$ref" : "flow.csv"}}}
