{"type":"Feature",
 "geometry":{"type":"Point","coordinates":[-121.900162576421,37.353960838763]},
 "properties":{"prmname":"HXI304",
 "description":null,
 "type":"Junction",
 "inflows":null,
 "sinks":null,
 "flow":{"$ref" : "flow.csv"}}}
