{"type":"Feature",
 "geometry":{"type":"Point","coordinates":[-121.740767522538,37.3451222402293]},
 "properties":{"prmname":"HXI304",
 "description":null,
 "type":"Junction",
 "inflows":null,
 "sinks":null,
 "flow":{"$ref" : "flow.csv"}}}
