{"type":"Feature",
 "geometry":{"type":"Point","coordinates":[-120.321487789062,37.1313881427344]},
 "properties":{"prmname":"CVPM13G",
 "description":"junction node for CVPM 13",
 "type":"Agricultural Demand",
 "inflows":null,
 "sinks":null}}
