{"type":"Feature",
 "geometry":{"type":"Point","coordinates":[-120.966210847159,37.4948427114143]},
 "properties":{"prmname":"HSU305D645",
 "description":"Hidden node on surface water conveyance channel",
 "type":"Junction",
 "inflows":null,
 "sinks":null,
 "flow":null}}
