{
  "type": "Feature",
  "geometry": {
    "type": "Point",
    "coordinates": [
      -116.740230098233,
      34.9580977952702
    ]
  },
  "properties": {
    "prmname": "GW-VC",
    "description": "Ventura County Groundwater",
    "type": "Groundwater Storage",
    "origins": [
      "ERes:VENT"
    ],
    "terminals": [
      "T55VENT"
    ],
    "initialstorage": 275,
    "endingstorage": 275,
    "inflows": [
      {
        "name": "Ventura Groundwater Inflows",
        "date": {
          "$ref": "inflows_0_date.json"
        },
        "inflow": {
          "$ref": "inflows_0_inflow.json"
        }
      }
    ],
    "costs": {
      "type": "Constant",
      "cost": 0
    },
    "constraints": {
      "constraint_type": "Bounded",
      "lower": {
        "bound_type": "None"
      },
      "upper": {
        "bound_type": "Constant",
        "bound": 10000
      }
    }
  }
}