{
  "type": "Feature",
  "geometry": {
    "type": "Point",
    "coordinates": [
      -119.955927737966,
      36.2145022881009
    ]
  },
  "properties": {
    "prmname": "HSU15C75",
    "description": "Hidden node on surface water conveyance channel",
    "type": "Junction",
    "origins": [
      "C75"
    ],
    "terminals": [
      "C90",
      "CVPM15"
    ],
    "inflows": null
  }
}