{"type":"Feature",
 "geometry":{"type":"Point","coordinates":[-119.917994,37.199946]},
 "properties":{"prmname":"SR_HID",
 "description":"Hensley Lake",
 "type":"Surface Storage",
 "initialstorage":24,
 "endingstorage":39.1199989318848,
 "areacapfactor":0.0134049998596311,
 "inflows":{"default":{"description":"Fresno River","inflow":{"$ref" : "inflows/default.csv"}}},
 "evaporation":{"$ref" : "evaporation.csv"},
 "el_ar_cap":{"$ref" : "elevation_area_capacity.csv"},
 "storage":{"$ref" : "storage.csv"},
 "costs":{ "type":"Monthly Variable","costs":{"JAN":{"$ref":"costs/JAN.csv"},"FEB":{"$ref":"costs/FEB.csv"},"MAR":{"$ref":"costs/MAR.csv"},"APR":{"$ref":"costs/APR.csv"},"MAY":{"$ref":"costs/MAY.csv"},"JUN":{"$ref":"costs/JUN.csv"},"JUL":{"$ref":"costs/JUL.csv"},"AUG":{"$ref":"costs/AUG.csv"},"SEP":{"$ref":"costs/SEP.csv"},"OCT":{"$ref":"costs/OCT.csv"},"NOV":{"$ref":"costs/NOV.csv"},"DEC":{"$ref":"costs/DEC.csv"}}},
 "bounds":[{"type":"LBC","bound":4},{"type":"UBT","bound": {"$ref":"./UBT.csv"}}],
 "sinks":null,
 "flow":null}}
