{"type":"Feature",
 "geometry":{"type":"Point","coordinates":[-121.143887874512,38.0540821232141]},
 "properties":{"prmname":"EXT_STOCK",
 "description":"Exterior urban return flows",
 "type":"Urban Demand",
 "inflows":null,
 "sinks":[{"default" : {"description" : null, "costs" : {"type":"Constant",
 "cost":0}, "bounds" : [{"type":"NOB"}], "flow" : {"$ref" : "./sinks/default/flow.csv"}}}],
 "flow":null}}
