{
  "type": "Feature",
  "geometry": {
    "type": "Point",
    "coordinates": [
      -122.187346354897,
      39.2606714671897
    ]
  },
  "properties": {
    "prmname": "GW-3",
    "description": "Central Valley groundwater basin",
    "type": "Groundwater Storage",
    "origins": [
      "CVPM3",
      "HGU3"
    ],
    "terminals": [
      "HGP3"
    ],
    "initialstorage": 132687,
    "endingstorage": 131748,
    "inflows": [
      {
        "name": "Groundwater inflow GW-3 based on C2VSIM Historical Run356",
        "date": {
          "$ref": "inflows_0_date.json"
        },
        "inflow": {
          "$ref": "inflows_0_inflow.json"
        }
      }
    ],
    "costs": {
      "type": "Constant",
      "cost": 0
    },
    "constraints": {
      "constraint_type": "Bounded",
      "lower": {
        "bound_type": "None"
      },
      "upper": {
        "bound_type": "None"
      }
    }
  }
}