{"type":"Feature",
 "geometry":{"type":"Point","coordinates":[-120.504382485558,36.6380091253656]},
 "properties":{"prmname":"HSU402AC92",
 "description":"Hidden node on surface water conveyance channel",
 "type":"Junction",
 "inflows":null,
 "sinks":null}}
