{
  "type": "Feature",
  "geometry": {
    "type": "Point",
    "coordinates": [
      -121.55711226186,
      39.9487984429982
    ]
  },
  "properties": {
    "prmname": "Sink G1",
    "description": "Depletion American River Folsom to Mouth",
    "type": "Sink",
    "origins": [
      "EXT STOCK",
      "D85"
    ],
    "terminals": null,
    "inflows": null
  }
}