{"type":"Feature",
 "geometry":{"type":"Point","coordinates":[-119.302143847159,36.6397821400699]},
 "properties":{"prmname":"HSD403",
 "description":"Hidden surface water calibration node",
 "type":"Junction",
 "inflows":null,
 "sinks":null,
 "flow":null}}
