{"type":"Feature",
 "geometry":{"type":"Point","coordinates":[-119.302144082456,36.6397816962289]},
 "properties":{"prmname":"HSD403",
 "description":"Hidden surface water calibration node",
 "type":"Junction",
 "inflows":null,
 "sinks":null,
 "flow":null}}
