{"type":"Feature",
 "geometry":{"type":"Point","coordinates":[-119.664885441333,36.3156462309206]},
 "properties":{"prmname":"HSD403",
 "description":"Hidden surface water calibration node",
 "type":"Junction",
 "inflows":null,
 "sinks":null,
 "flow":null}}
