{"type":"Feature",
 "geometry":{"type":"Point","coordinates":[-119.312786847159,36.6155362740303]},
 "properties":{"prmname":"HSD403",
 "description":"Hidden surface water calibration node",
 "type":"Junction",
 "inflows":null,
 "sinks":null,
 "flow":null}}
