{"type":"Feature",
 "geometry":{"type":"Point","coordinates":[-120.961185308957,37.7324324673312]},
 "properties":{"prmname":"HXI302",
 "description":null,
 "type":"Junction",
 "inflows":null,
 "sinks":null,
 "flow":null}}
