{"type":"Feature",
 "geometry":{"type":"Point","coordinates":[-120.955218956918,37.7227217131468]},
 "properties":{"prmname":"HXI302",
 "description":null,
 "type":"Junction",
 "inflows":null,
 "sinks":null,
 "flow":null}}
