{"type":"Feature",
 "geometry":{"type":"Point","coordinates":[-117.050673362434,36.0022942122475]},
 "properties":{"prmname":"EXT AV",
 "description":"DAU 299-307, Exterior Res/Landscape",
 "type":"Urban Demand",
 "inflows":null,
 "sinks":null,
 "flow":null}}
