{"type":"Feature",
 "geometry":{"type":"Point","coordinates":[-117.052919150644,36.0041110192872]},
 "properties":{"prmname":"EXT AV",
 "description":"DAU 299-307, Exterior Res/Landscape",
 "type":"Urban Demand",
 "inflows":null,
 "sinks":null,
 "flow":null}}
