{"type":"Feature",
 "geometry":{"type":"Point","coordinates":[-121.047761385017,37.6887877034723]},
 "properties":{"prmname":"WTP302",
 "description":null,
 "type":"Water Treatment",
 "inflows":null,
 "sinks":null,
 "flow":null}}
