{"type":"Feature",
 "geometry":{"type":"Point","coordinates":[-119.034337,35.209827]},
 "properties":{"prmname":"HGR21",
 "description":"Hidden node for calibration of GW-21",
 "type":"Junction",
 "inflows":null,
 "sinks":null,
 "flow":null}}
