{"type":"Feature",
 "geometry":{"type":"Point","coordinates":[-119.03433737227,35.2098270270203]},
 "properties":{"prmname":"HGR21",
 "description":"Hidden node for calibration of GW-21",
 "type":"Junction",
 "inflows":null,
 "sinks":null,
 "flow":null}}
