{"type":"Feature",
 "geometry":{"type":"Point","coordinates":[-119.034890364247,35.1764990505223]},
 "properties":{"prmname":"HGR21",
 "description":"Hidden node for calibration of GW-21",
 "type":"Junction",
 "inflows":null,
 "sinks":null,
 "flow":null}}
