{"type":"Feature",
 "geometry":{"type":"Point","coordinates":[-119.105153822711,35.3136542820669]},
 "properties":{"prmname":"HGR21",
 "description":"Hidden node for calibration of GW-21",
 "type":"Junction",
 "inflows":null,
 "sinks":null,
 "flow":null}}
