{"type":"Feature",
 "geometry":{"type":"Point","coordinates":[-120.20875743811,36.5839217857552]},
 "properties":{"prmname":"HSD402B",
 "description":null,
 "type":"Junction",
 "inflows":null,
 "sinks":null,
 "flow":null}}
