{"type":"Feature",
 "geometry":{"type":"Point","coordinates":[-119.951647,36.381862]},
 "properties":{"prmname":"HSD402B",
 "description":null,
 "type":"Junction",
 "inflows":null,
 "sinks":null,
 "flow":null}}
