{
  "type": "Feature",
  "geometry": {
    "type": "Point",
    "coordinates": [
      -119.248868576421,
      35.7564414309177
    ]
  },
  "properties": {
    "prmname": "HNP407",
    "description": null,
    "type": "Junction",
    "inflows": null,
    "sinks": null,
    "flow": {
      "$ref": "flow.csv"
    }
  }
}