{"type":"Feature",
 "geometry":{"type":"Point","coordinates":[-119.115426357029,35.6183748028621]},
 "properties":{"prmname":"HNP407",
 "description":null,
 "type":"Junction",
 "inflows":null,
 "sinks":null,
 "flow":null}}
