{"type":"Feature",
 "geometry":{"type":"Point","coordinates":[-119.11767214524,35.6147234540167]},
 "properties":{"prmname":"HNP407",
 "description":null,
 "type":"Junction",
 "inflows":null,
 "sinks":null,
 "flow":null}}
