{"type":"Feature",
 "geometry":{"type":"Point","coordinates":[-117.023927807535,33.6097235320351]},
 "properties":{"prmname":"HSU509C154",
 "description":null,
 "type":"Junction",
 "inflows":null,
 "sinks":null,
 "flow":null}}
