{"type":"Feature",
 "geometry":{"type":"Point","coordinates":[-121.973696405384,38.47818868625]},
 "properties":{"prmname":"EXT CVPM06",
 "description":"100% of DAU 162, 9% of DAU 191, 40 & 41, exterior",
 "type":"Urban Demand",
 "inflows":null,
 "sinks":null,
 "flow":null}}
