{"type":"Feature",
 "geometry":{"type":"Point","coordinates":[-121.975942193594,38.4799467690588]},
 "properties":{"prmname":"EXT CVPM06",
 "description":"100% of DAU 162, 9% of DAU 191, 40 & 41, exterior",
 "type":"Urban Demand",
 "inflows":null,
 "sinks":null,
 "flow":null}}
