{
  "type": "Feature",
  "geometry": {
    "type": "Point",
    "coordinates": [
      -121.921118576421,
      38.3379405019727
    ]
  },
  "properties": {
    "prmname": "HXI205",
    "description": null,
    "type": "Junction",
    "inflows": null,
    "sinks": null,
    "flow": {
      "$ref": "flow.csv"
    }
  }
}