{"type":"Feature",
 "geometry":{"type":"Point","coordinates":[-121.735031991741,39.1709072714747]},
 "properties":{"prmname":"HSR201",
 "description":"Hidden surface water node for Gray Lodge Refuge",
 "type":"Junction",
 "inflows":null,
 "sinks":null,
 "flow":null}}
