{"type":"Feature",
 "geometry":{"type":"Point","coordinates":[-121.674853956627,39.272092136017]},
 "properties":{"prmname":"HSR201",
 "description":"Hidden surface water node for Gray Lodge Refuge",
 "type":"Junction",
 "inflows":null,
 "sinks":null,
 "flow":null}}
