{"type":"Feature",
 "geometry":{"type":"Point","coordinates":[-121.649280517123,39.2725949280545]},
 "properties":{"prmname":"HSR201",
 "description":"Hidden surface water node for Gray Lodge Refuge",
 "type":"Junction",
 "inflows":null,
 "sinks":null,
 "flow":null}}
