{
  "type": "Feature",
  "geometry": {
    "type": "Point",
    "coordinates": [
      -118.044482,
      33.906477
    ]
  },
  "properties": {
    "prmname": "HGPMWD",
    "description": null,
    "type": "Junction",
    "inflows": null,
    "sinks": null,
    "flow": {
      "$ref": "flow.csv"
    }
  }
}