{"type":"Feature",
 "geometry":{"type":"Point","coordinates":[-119.848627576421,36.1922382006577]},
 "properties":{"prmname":"CVPM15BG",
 "description":null,
 "type":"Agricultural Demand",
 "inflows":null,
 "sinks":null,
 "flow":null}}
