{"type":"Feature",
 "geometry":{"type":"Point","coordinates":[-119.786142576421,36.1939002775994]},
 "properties":{"prmname":"CVPM15BG",
 "description":null,
 "type":"Agricultural Demand",
 "inflows":null,
 "sinks":null,
 "flow":null}}
