{"type":"Feature",
 "geometry":{"type":"Point","coordinates":[-119.848627215937,36.1922380427586]},
 "properties":{"prmname":"CVPM15BG",
 "description":null,
 "type":"Agricultural Demand",
 "inflows":null,
 "sinks":null,
 "flow":null}}
