{"type":"Feature",
 "geometry":{"type":"Point","coordinates":[-119.848627215936,36.1994874736529]},
 "properties":{"prmname":"CVPM15BG",
 "description":null,
 "type":"Agricultural Demand",
 "inflows":null,
 "sinks":null,
 "flow":null}}
