{"type":"Feature",
 "geometry":{"type":"Point","coordinates":[-119.846381427726,36.1976751788566]},
 "properties":{"prmname":"CVPM15BG",
 "description":null,
 "type":"Agricultural Demand",
 "inflows":null,
 "sinks":null,
 "flow":null}}
