{
  "type": "Feature",
  "geometry": {
    "type": "Point",
    "coordinates": [
      -121.196111475859,
      38.3800905661228
    ]
  },
  "properties": {
    "prmname": "EXT CVPM8",
    "description": "100% of DAU 180, exterior",
    "type": "Urban Demand",
    "origins": [
      "T43GALT"
    ],
    "terminals": [
      "HGU8"
    ],
    "inflows": null
  }
}