{"type":"Feature",
 "geometry":{"type":"Point","coordinates":[-121.504492963506,37.0700419970342]},
 "properties":{"prmname":"HGRSC",
 "description":null,
 "type":"Junction",
 "inflows":null,
 "sinks":null,
 "flow":null}}
