{
  "type": "Feature",
  "geometry": {
    "type": "Point",
    "coordinates": [
      -121.790241,
      37.404386
    ]
  },
  "properties": {
    "prmname": "HGRSC",
    "description": null,
    "type": "Junction",
    "inflows": null,
    "sinks": null,
    "flow": {
      "$ref": "flow.csv"
    }
  }
}