{"type":"Feature",
 "geometry":{"type":"Point","coordinates":[-121.797657064229,37.3992708531523]},
 "properties":{"prmname":"HGRSC",
 "description":null,
 "type":"Junction",
 "inflows":null,
 "sinks":null,
 "flow":null}}
