{"type":"Feature",
 "geometry":{"type":"Point","coordinates":[-121.79024129451,37.4043857545628]},
 "properties":{"prmname":"HGRSC",
 "description":null,
 "type":"Junction",
 "inflows":null,
 "sinks":null,
 "flow":null}}
