{
  "type": "Feature",
  "geometry": {
    "type": "Point",
    "coordinates": [
      -121.678385850506,
      39.3219682468551
    ]
  },
  "properties": {
    "prmname": "CVPM5",
    "description": "CVPM5 Agricultural Demand",
    "type": "Agricultural Demand",
    "origins": [
      "HSU5D31",
      "HGP5",
      "HSU5SR-6",
      "HSU5C83",
      "HSU5C80",
      "HSU5C77",
      "HSU5C35"
    ],
    "terminals": [
      "C307",
      "GW-5"
    ],
    "costs": {
      "type": "Monthly Variable",
      "costs": {
        "$ref": "costs_costs.json"
      }
    },
    "constraints": {
      "constraint_type": "Bounded",
      "lower": null,
      "upper": {
        "bound_type": "TimeSeries",
        "date": {
          "$ref": "constraints_upper_date.json"
        },
        "bound": {
          "$ref": "constraints_upper_bound.json"
        }
      }
    }
  }
}