{"type":"Feature",
 "geometry":{"type":"Point","coordinates":[-120.882669987779,37.5217753657482]},
 "properties":{"prmname":"HSU305D699",
 "description":"Hidden node on surface water conveyance channel",
 "type":"Junction",
 "inflows":null,
 "sinks":null,
 "flow":null}}
