{"type":"Feature",
 "geometry":{"type":"Point","coordinates":[-122.322692365475,39.9796829015754]},
 "properties":{"prmname":"HGP02",
 "description":"Hidden calibration for GW-2",
 "type":"Junction",
 "inflows":null,
 "sinks":null,
 "flow":{"$ref" : "flow.csv"}}}
