{
  "type": "Feature",
  "geometry": {
    "type": "Point",
    "coordinates": [
      -122.246722,
      39.9021579999999
    ]
  },
  "properties": {
    "prmname": "HGP02",
    "description": "Hidden calibration for GW-2",
    "type": "Junction",
    "inflows": null,
    "sinks": null,
    "flow": {
      "$ref": "flow.csv"
    }
  }
}