{"type":"Feature",
 "geometry":{"type":"Point","coordinates":[-122.258737350431,39.9877028291239]},
 "properties":{"prmname":"HGP02",
 "description":"Hidden calibration for GW-2",
 "type":"Junction",
 "inflows":null,
 "sinks":null}}
