{"type":"Feature",
 "geometry":{"type":"Point","coordinates":[-120.8318046042,37.1468014748986]},
 "properties":{"prmname":"HSU303C30",
 "description":"Hidden node on surface water conveyance channel",
 "type":"Junction",
 "inflows":null,
 "sinks":null,
 "flow":{"$ref" : "flow.csv"}}}
