{"type":"Feature",
 "geometry":{"type":"Point","coordinates":[-121.888372136571,38.5780035296979]},
 "properties":{"prmname":"HSD203",
 "description":"Hidden surface water calibration node",
 "type":"Junction",
 "inflows":null,
 "sinks":null,
 "flow":null}}
