{
  "type": "Feature",
  "geometry": {
    "type": "Point",
    "coordinates": [
      -121.888371847159,
      38.5780034202923
    ]
  },
  "properties": {
    "prmname": "HSD203",
    "description": "Hidden surface water calibration node",
    "type": "Junction",
    "inflows": null,
    "sinks": null,
    "flow": {
      "$ref": "flow.csv"
    }
  }
}