{"type":"Feature",
 "geometry":{"type":"Point","coordinates":[-121.892863712991,38.5622007867431]},
 "properties":{"prmname":"HSD203",
 "description":"Hidden surface water calibration node",
 "type":"Junction",
 "inflows":null,
 "sinks":null,
 "flow":null}}
