{"type":"Feature",
 "geometry":{"type":"Point","coordinates":[-121.888371847159,38.5815142486643]},
 "properties":{"prmname":"HSD203",
 "description":"Hidden surface water calibration node",
 "type":"Junction",
 "inflows":null,
 "sinks":null,
 "flow":null}}
