{"type":"Feature",
 "geometry":{"type":"Point","coordinates":[-121.775696529052,38.528221915915]},
 "properties":{"prmname":"HSD203",
 "description":"Hidden surface water calibration node",
 "type":"Junction",
 "inflows":null,
 "sinks":null,
 "flow":null}}
