{"type":"Feature",
 "geometry":{"type":"Point","coordinates":[-117.029964545956,33.6847161375691]},
 "properties":{"prmname":"SR-DMV",
 "description":"Diamond Valley Lake (Formerly Eastside reservoir)",
 "type":"Surface Storage",
 "initialstorage":600,
 "endingstorage":600,
 "areacapfactor":0.00508,
 "inflows":null,
 "el_ar_cap":{"$ref":"elevation_area_capacity.csv"},
 "costs":{ "type":"Annual Variable","costs":{"JAN-DEC":{"$ref":"cost_JAN-DEC.csv"}}},
 "bounds":[{"type":"LBC","bound":230.4},{"type":"UBC","bound":825}],
 "sinks":null}}
