{
  "type": "Feature",
  "geometry": {
    "type": "Point",
    "coordinates": [
      -117.688204369656,
      33.7992227312183
    ]
  },
  "properties": {
    "prmname": "Sink G30",
    "description": "VENTURA outflow (to ocean)",
    "type": "Sink",
    "origins": [
      "IND:VENT"
    ],
    "terminals": null,
    "inflows": null
  }
}