{"type":"Feature",
 "geometry":{"type":"Point","coordinates":[-119.817738588874,36.7492567564028]},
 "properties":{"prmname":"CVPM16S",
 "description":"junction node for CVPM 16",
 "type":"Agricultural Demand",
 "inflows":null,
 "sinks":null,
 "flow":null}}
