{"type":"Feature",
 "geometry":{"type":"Point","coordinates":[-118.163847710639,36.450236408675]},
 "properties":{"prmname":"AgS_Owens",
 "description":"Owens Valley Ag",
 "type":"Agricultural Demand",
 "inflows":null,
 "sinks":[{"AgS_Owens" : {"description":null,"costs":{"type":"Constant",
 "cost":0},"bounds":[{"type":"NOB"}],"flow":{"$ref" : "./sinks/AgS_Owens/flow.csv"}}}],
 "flow":null}}
