{"type":"Feature",
 "geometry":{"type":"Point","coordinates":[-118.16609349885,36.4484299358282]},
 "properties":{"prmname":"AgS: Owens",
 "description":"Owens Valley Ag",
 "type":"Agricultural Demand",
 "inflows":null,
 "sinks":{"default":{"description":null,"costs":{"type":"Constant",
 "cost":0},"bounds":[{"type":"NOB"}]}},
 "flow":null}}
