{"type":"Feature",
 "geometry":{"type":"Point","coordinates":[-118.398107423579,37.3451353002406]},
 "properties":{"prmname":"AgS_Owens",
 "description":"Owens Valley Ag",
 "type":"Agricultural Demand",
 "inflows":null,
 "sinks":[{"default" : {"description" : null, "costs" : {"type":"Constant",
 "cost":0}, "bounds" : [{"type":"NOB"}], "flow" : {"$ref" : "./sinks/default/flow.csv"}}}],
 "flow":null}}
