{
  "type": "Feature",
  "geometry": {
    "type": "Point",
    "coordinates": [
      -116.153681837567,
      33.6339070203996
    ]
  },
  "properties": {
    "prmname": "HWTC147",
    "description": "Hidden node for higher cost direct use of Coachella Canal surface water via water treatment plant to Coachella Urban, in parrallel with existing direct use for gold course irrigation from C147; for future scenarios of 2100.",
    "type": "Junction",
    "origins": [
      "C147"
    ],
    "terminals": [
      "T31COAC"
    ],
    "inflows": null
  }
}