{"type":"Feature",
 "geometry":{"type":"Point","coordinates":[-120.268021343829,37.5839345149061]},
 "properties":{"prmname":"SR-MCR",
 "description":"Lake McClure",
 "type":"Surface Storage",
 "initialstorage":229,
 "endingstorage":834.59,
 "areacapfactor":0.00638,
 "inflows":{"default":{"description":"Merced River","inflow":{"$ref" : "inflow_default.csv"}}},
 "el_ar_cap":{"$ref":"elevation_area_capacity.csv"},
 "costs":{ "type":"Monthly Variable","costs":{"JAN":{"$ref":"cost_JAN.csv"},"FEB":{"$ref":"cost_FEB.csv"},"MAR":{"$ref":"cost_MAR.csv"},"APR":{"$ref":"cost_APR.csv"},"MAY":{"$ref":"cost_MAY.csv"},"JUN":{"$ref":"cost_JUN.csv"},"JUL":{"$ref":"cost_JUL.csv"},"AUG":{"$ref":"cost_AUG.csv"},"SEP":{"$ref":"cost_SEP.csv"},"OCT":{"$ref":"cost_OCT.csv"},"NOV":{"$ref":"cost_NOV.csv"},"DEC":{"$ref":"cost_DEC.csv"}}},
 "bounds":[{"type":"LBC","bound":115},{"type":"UBT","bound": {"$ref":"./UBT.csv"}}],
 "sinks":null}}
