{"type":"Feature",
 "geometry":{"type":"Point","coordinates":[-120.706070535435,35.7074505158318]},
 "properties":{"prmname":"SinkG6",
 "description":"California Aqueduct losses R3",
 "type":"Sink",
 "inflows":null,
 "sinks":null}}
