{
  "type": "Feature",
  "geometry": {
    "type": "Point",
    "coordinates": [
      -122.123076,
      37.729929
    ]
  },
  "properties": {
    "prmname": "SR_EBMUD",
    "description": "EBMUD aggregate",
    "type": "Surface Storage",
    "initialstorage": 117.900001525879,
    "endingstorage": 117.900001525879,
    "areacapfactor": 0.0107391700148582,
    "inflows": null,
    "evaporation": {
      "$ref": "evaporation.csv"
    },
    "el_ar_cap": {
      "$ref": "elevation_area_capacity.csv"
    },
    "storage": {
      "$ref": "storage.csv"
    },
    "costs": {
      "type": "Monthly Variable",
      "costs": {
        "JAN": {
          "$ref": "costs/JAN.csv"
        },
        "FEB": {
          "$ref": "costs/FEB.csv"
        },
        "MAR": {
          "$ref": "costs/MAR.csv"
        },
        "APR": {
          "$ref": "costs/APR.csv"
        },
        "MAY": {
          "$ref": "costs/MAY.csv"
        },
        "JUN": {
          "$ref": "costs/JUN.csv"
        },
        "JUL": {
          "$ref": "costs/JUL.csv"
        },
        "AUG": {
          "$ref": "costs/AUG.csv"
        },
        "SEP": {
          "$ref": "costs/SEP.csv"
        },
        "OCT": {
          "$ref": "costs/OCT.csv"
        },
        "NOV": {
          "$ref": "costs/NOV.csv"
        },
        "DEC": {
          "$ref": "costs/DEC.csv"
        }
      }
    },
    "bounds": [
      {
        "type": "LBC",
        "bound": 83
      },
      {
        "type": "UBM",
        "bound": {
          "$ref": "./UBM.csv"
        }
      }
    ],
    "sinks": null,
    "flow": {
      "$ref": "flow.csv"
    }
  }
}