{"type":"Feature",
 "geometry":{"type":"Point","coordinates":[-119.112334290118,35.5941549850946]},
 "properties":{"prmname":"HXI407",
 "description":null,
 "type":"Junction",
 "inflows":null,
 "sinks":null,
 "flow":null}}
