{"type":"Feature",
 "geometry":{"type":"Point","coordinates":[-117.11200458163,33.7176796323232]},
 "properties":{"prmname":"WWP509",
 "description":"E and W MWD OUT",
 "type":"Water Treatment",
 "inflows":null,
 "sinks":{"default":{"description":"SW discharge to Ocean","costs":{"type":"Constant",
 "cost":0},"bounds":[{"type":"NOB"}]}},
 "flow":null}}
