{"type":"Feature",
 "geometry":{"type":"Point","coordinates":[-121.516339181868,38.1144272993193]},
 "properties":{"prmname":"HSU206D515",
 "description":"Hidden node on surface water conveyance channel",
 "type":"Junction",
 "inflows":null,
 "sinks":null}}
