{"type":"Feature",
 "geometry":{"type":"Point","coordinates":[-121.388785847159,38.8374632709424]},
 "properties":{"prmname":"HSU204C33",
 "description":"Hidden node on surface water conveyance channel",
 "type":"Junction",
 "inflows":null,
 "sinks":null,
 "flow":null}}
