{
  "type": "Feature",
  "geometry": {
    "type": "Point",
    "coordinates": [
      -117.862728451475,
      34.0343816478517
    ]
  },
  "properties": {
    "prmname": "T5CMWD",
    "description": "Central MWD IN",
    "type": "Water Treatment",
    "origins": [
      "DesalR5",
      "GW-MWD",
      "T10CMWD",
      "C161",
      "HWWT10"
    ],
    "terminals": [
      "Ind: CMWD",
      "HXCMWD",
      "IRes CMWD"
    ],
    "inflows": null
  }
}