{"type":"Feature",
 "geometry":{"type":"Point","coordinates":[-117.122752400536,33.7276366171722]},
 "properties":{"prmname":"HGREW",
 "description":null,
 "type":"Junction",
 "inflows":null,
 "sinks":null,
 "flow":null}}
