{"type":"Feature",
 "geometry":{"type":"Point","coordinates":[-117.120133,33.715588]},
 "properties":{"prmname":"HGREW",
 "description":null,
 "type":"Junction",
 "inflows":null,
 "sinks":null,
 "flow":null}}
