{"type":"Feature",
 "geometry":{"type":"Point","coordinates":[-117.185501857659,33.7856963867598]},
 "properties":{"prmname":"HGREW",
 "description":null,
 "type":"Junction",
 "inflows":null,
 "sinks":null,
 "flow":null}}
