{
  "type": "Feature",
  "geometry": {
    "type": "Point",
    "coordinates": [
      -120.321487789062,
      37.1313881427344
    ]
  },
  "properties": {
    "prmname": "GW-13",
    "description": "Central Valley groundwater basin",
    "type": "Groundwater Storage",
    "origins": [
      "HAR13",
      "CVPM13",
      "HGU13"
    ],
    "terminals": [
      "HGP13"
    ],
    "initialstorage": 138216,
    "endingstorage": 128560,
    "inflows": [
      {
        "name": "Groundwater inflow GW-13 C2VSIM Historical Run ",
        "date": {
          "$ref": "inflows_0_date.json"
        },
        "inflow": {
          "$ref": "inflows_0_inflow.json"
        }
      }
    ],
    "costs": {
      "type": "Constant",
      "cost": 0
    },
    "constraints": {
      "constraint_type": "Bounded",
      "lower": {
        "bound_type": "None"
      },
      "upper": {
        "bound_type": "None"
      }
    }
  }
}