{
  "type": "Feature",
  "geometry": {
    "type": "Point",
    "coordinates": [
      -117.701517576421,
      33.5282709011569
    ]
  },
  "properties": {
    "prmname": "HXI509",
    "description": null,
    "type": "Junction",
    "inflows": null,
    "sinks": null,
    "flow": {
      "$ref": "flow.csv"
    }
  }
}