{"type":"Feature",
 "geometry":{"type":"Point","coordinates":[-121.043811659458,38.3868140079807]},
 "properties":{"prmname":"HXI207",
 "description":null,
 "type":"Junction",
 "inflows":null,
 "sinks":null,
 "flow":null}}
