{"type":"Feature",
 "geometry":{"type":"Point","coordinates":[-122.332208858817,40.4597027081475]},
 "properties":{"prmname":"HSU101D74",
 "description":"Hidden node on surface water conveyance channel",
 "type":"Junction",
 "inflows":null,
 "sinks":null}}
