{"type":"Feature",
 "geometry":{"type":"Point","coordinates":[-117.965618285195,35.1624770544421]},
 "properties":{"prmname":"AGG AV",
 "description":"Antelope Valley Ag supplied by GW",
 "type":"Agricultural Demand",
 "inflows":null,
 "sinks":null,
 "flow":null}}
