{"type":"Feature",
 "geometry":{"type":"Point","coordinates":[-119.281755177136,36.1148811825802]},
 "properties":{"prmname":"HGP18",
 "description":"Hidden node for calibration of GW-18",
 "type":"Junction",
 "inflows":null,
 "sinks":null,
 "flow":{"$ref" : "flow.csv"}}}
