{"type":"Feature",
 "geometry":{"type":"Point","coordinates":[-119.258115,36.164255]},
 "properties":{"prmname":"HGP18",
 "description":"Hidden node for calibration of GW-18",
 "type":"Junction",
 "inflows":null,
 "sinks":null,
 "flow":{"$ref" : "flow.csv"}}}
