{
  "type": "Feature",
  "geometry": {
    "type": "Point",
    "coordinates": [
      -119.113180568819,
      35.6220259850101
    ]
  },
  "properties": {
    "prmname": "GW-20",
    "description": "Central Valley groundwater basin",
    "type": "Groundwater Storage",
    "origins": [
      "HAR20",
      "HGU20",
      "CVPM20"
    ],
    "terminals": [
      "HGP20"
    ],
    "initialstorage": 137073,
    "endingstorage": 125136,
    "inflows": [
      {
        "name": "Groundwater inflow GW-20 C2VSIM Historical Run356",
        "date": {
          "$ref": "inflows_0_date.json"
        },
        "inflow": {
          "$ref": "inflows_0_inflow.json"
        }
      }
    ],
    "costs": {
      "type": "Constant",
      "cost": 0
    },
    "constraints": {
      "constraint_type": "Bounded",
      "lower": {
        "bound_type": "None"
      },
      "upper": {
        "bound_type": "None"
      }
    }
  }
}