{"type":"Feature",
 "geometry":{"type":"Point","coordinates":[-119.375776471449,35.4803363275348]},
 "properties":{"prmname":"HSU408AN12",
 "description":"Hidden node on surface water conveyance channel",
 "type":"Junction",
 "inflows":null,
 "sinks":null,
 "flow":null}}
