{
  "type": "Feature",
  "geometry": {
    "type": "Point",
    "coordinates": [
      -119.551324,
      35.508649
    ]
  },
  "properties": {
    "prmname": "HSU408AN12",
    "description": "Hidden node on surface water conveyance channel",
    "type": "Junction",
    "inflows": null,
    "sinks": null,
    "flow": {
      "$ref": "flow.csv"
    }
  }
}