{"type":"Feature",
 "geometry":{"type":"Point","coordinates":[-119.482521909516,35.4032785652661]},
 "properties":{"prmname":"HSU408AN12",
 "description":"Hidden node on surface water conveyance channel",
 "type":"Junction",
 "inflows":null,
 "sinks":null,
 "flow":null}}
