{"type":"Feature",
 "geometry":{"type":"Point","coordinates":[-119.520076361955,35.4589157332052]},
 "properties":{"prmname":"HGP19",
 "description":"Hidden node for calibration of GW-19",
 "type":"Junction",
 "inflows":null,
 "sinks":null,
 "flow":{"$ref" : "flow.csv"}}}
