{"type":"Feature",
 "geometry":{"type":"Point","coordinates":[-119.528461385292,35.4917756157559]},
 "properties":{"prmname":"HGP19",
 "description":"Hidden node for calibration of GW-19",
 "type":"Junction",
 "inflows":null,
 "sinks":null}}
