{"type":"Feature",
 "geometry":{"type":"Point","coordinates":[-121.905628044003,38.5339303517296]},
 "properties":{"prmname":"WTP203",
 "description":null,
 "type":"Water Treatment",
 "inflows":null,
 "sinks":null,
 "flow":null}}
