{
  "type": "Feature",
  "geometry": {
    "type": "Point",
    "coordinates": [
      -115.562354571647,
      33.8813022108897
    ]
  },
  "properties": {
    "prmname": "Sink G51",
    "description": "COLORADO RIVER outflow",
    "type": "Sink",
    "origins": [
      "Mexico"
    ],
    "terminals": null,
    "inflows": null
  }
}