{"type":"Feature",
 "geometry":{"type":"Point","coordinates":[-117.904462554508,34.0305933886675]},
 "properties":{"prmname":"HGPSD",
 "description":null,
 "type":"Junction",
 "inflows":null,
 "sinks":null,
 "flow":{"$ref" : "flow.csv"}}}
