{"type":"Feature",
 "geometry":{"type":"Point","coordinates":[-117.732629634779,33.9365021495557]},
 "properties":{"prmname":"HARMWD",
 "description":null,
 "type":"Junction",
 "inflows":null,
 "sinks":null,
 "flow":null}}
