{"type":"Feature",
 "geometry":{"type":"Point","coordinates":[-121.03827332497,38.3862164500698]},
 "properties":{"prmname":"HSU207C37",
 "description":"Hidden node on surface water conveyance channel",
 "type":"Junction",
 "inflows":null,
 "sinks":null,
 "flow":null}}
