{"type":"Feature",
 "geometry":{"type":"Point","coordinates":[-117.607300255292,34.5566228591855]},
 "properties":{"prmname":"WTP506",
 "description":null,
 "type":"Water Treatment",
 "inflows":null,
 "sinks":null,
 "flow":null}}
