{"type":"Feature",
 "geometry":{"type":"Point","coordinates":[-117.602808678871,34.5575476314881]},
 "properties":{"prmname":"WTP506",
 "description":null,
 "type":"Water Treatment",
 "inflows":null,
 "sinks":null,
 "flow":null}}
