{"type":"Feature",
 "geometry":{"type":"Point","coordinates":[-117.605054467081,34.5575476314882]},
 "properties":{"prmname":"WTP506",
 "description":null,
 "type":"Water Treatment",
 "inflows":null,
 "sinks":null,
 "flow":null}}
