{"type":"Feature",
 "geometry":{"type":"Point","coordinates":[-117.363541635369,34.4886610851199]},
 "properties":{"prmname":"WTP506",
 "description":null,
 "type":"Water Treatment",
 "inflows":null,
 "sinks":null,
 "flow":null}}
