{
  "type": "Feature",
  "geometry": {
    "type": "Point",
    "coordinates": [
      -117.855308844616,
      34.2384287163205
    ]
  },
  "properties": {
    "prmname": "HXCMWD",
    "description": "Hidden node for year type variation in demand, central mwd",
    "type": "Junction",
    "origins": [
      "T5CMWD"
    ],
    "terminals": [
      "ERes: CMWD"
    ],
    "inflows": [
      {
        "name": "Year type variation for Central MWD",
        "date": {
          "$ref": "inflows_0_date.json"
        },
        "inflow": {
          "$ref": "inflows_0_inflow.json"
        }
      }
    ]
  }
}