{"type":"Feature",
 "geometry":{"type":"Point","coordinates":[-116.174018449357,34.680415818533]},
 "properties":{"prmname":"INT MR",
 "description":"DAU 308-332 Ind/Interior Res/Comm demand",
 "type":"Urban Demand",
 "inflows":null,
 "sinks":null}}
