{"type":"Feature",
 "geometry":{"type":"Point","coordinates":[-121.969877849274,38.4208310909392]},
 "properties":{"prmname":"HGP06",
 "description":"Hidden node for calibration of GW-6",
 "type":"Junction",
 "inflows":null,
 "sinks":null,
 "flow":{"$ref" : "flow.csv"}}}
