{
  "type": "Feature",
  "geometry": {
    "type": "Point",
    "coordinates": [
      -121.882675,
      38.532374
    ]
  },
  "properties": {
    "prmname": "HGP06",
    "description": "Hidden node for calibration of GW-6",
    "type": "Junction",
    "inflows": null,
    "sinks": null,
    "flow": {
      "$ref": "flow.csv"
    }
  }
}