{"type":"Feature",
 "geometry":{"type":"Point","coordinates":[-121.969763027808,38.4760218254506]},
 "properties":{"prmname":"HGP06",
 "description":"Hidden node for calibration of GW-6",
 "type":"Junction",
 "inflows":null,
 "sinks":null,
 "flow":{"$ref" : "flow.csv"}}}
