{"type":"Feature",
 "geometry":{"type":"Point","coordinates":[-122.06595821894,38.372252661554]},
 "properties":{"prmname":"HGP06",
 "description":"Hidden node for calibration of GW-6",
 "type":"Junction",
 "inflows":null,
 "sinks":null,
 "flow":{"$ref" : "flow.csv"}}}
