{"type":"Feature",
 "geometry":{"type":"Point","coordinates":[-120.106749576421,36.1966799803845]},
 "properties":{"prmname":"HNP402",
 "description":null,
 "type":"Junction",
 "inflows":null,
 "sinks":null,
 "flow":null}}
