{"type":"Feature",
 "geometry":{"type":"Point","coordinates":[-120.229155642624,36.3232237082597]},
 "properties":{"prmname":"HNP402",
 "description":null,
 "type":"Junction",
 "inflows":null,
 "sinks":null,
 "flow":null}}
