{"type":"Feature",
 "geometry":{"type":"Point","coordinates":[-120.23255893221,36.3215948130289]},
 "properties":{"prmname":"HNP402",
 "description":null,
 "type":"Junction",
 "inflows":null,
 "sinks":null,
 "flow":null}}
