{"type":"Feature",
 "geometry":{"type":"Point","coordinates":[-120.234804720421,36.3179758430052]},
 "properties":{"prmname":"HNP402",
 "description":null,
 "type":"Junction",
 "inflows":null,
 "sinks":null,
 "flow":null}}
