{"type":"Feature",
 "geometry":{"type":"Point","coordinates":[-120.230994818162,36.3116747074532]},
 "properties":{"prmname":"HNP402",
 "description":null,
 "type":"Junction",
 "inflows":null,
 "sinks":null,
 "flow":null}}
