{
  "type": "Feature",
  "geometry": {
    "type": "Point",
    "coordinates": [
      -119.7854,
      36.15417
    ]
  },
  "properties": {
    "prmname": "HSD404B",
    "description": null,
    "type": "Junction",
    "inflows": null,
    "sinks": null,
    "flow": {
      "$ref": "flow.csv"
    }
  }
}