{"type":"Feature",
 "geometry":{"type":"Point","coordinates":[-119.444207803496,36.203313753647]},
 "properties":{"prmname":"HSD404B",
 "description":null,
 "type":"Junction",
 "inflows":null,
 "sinks":null,
 "flow":null}}
