{"type":"Feature",
 "geometry":{"type":"Point","coordinates":[-119.831823971986,36.1101467035129]},
 "properties":{"prmname":"HSD404B",
 "description":null,
 "type":"Junction",
 "inflows":null,
 "sinks":null,
 "flow":null}}
