{"type":"Feature",
 "geometry":{"type":"Point","coordinates":[-119.484649,36.259161]},
 "properties":{"prmname":"HSD404B",
 "description":null,
 "type":"Junction",
 "inflows":null,
 "sinks":null,
 "flow":null}}
