{"type":"Feature",
 "geometry":{"type":"Point","coordinates":[-121.518080223416,39.5328862108153]},
 "properties":{"prmname":"SR_ORO",
 "description":"Lake Oroville",
 "type":"Surface Storage",
 "initialstorage":2555,
 "endingstorage":2633.35009765625,
 "areacapfactor":0.00406499998643994,
 "inflows":null,
 "evaporation":{"$ref" : "evaporation.csv"},
 "el_ar_cap":{"$ref" : "elevation_area_capacity.csv"},
 "storage":{"$ref" : "storage.csv"},
 "costs":{ "type":"Monthly Variable","costs":{"JAN":{"$ref":"costs/JAN.csv"},"FEB":{"$ref":"costs/FEB.csv"},"MAR":{"$ref":"costs/MAR.csv"},"APR":{"$ref":"costs/APR.csv"},"MAY":{"$ref":"costs/MAY.csv"},"JUN":{"$ref":"costs/JUN.csv"},"JUL":{"$ref":"costs/JUL.csv"},"AUG":{"$ref":"costs/AUG.csv"},"SEP":{"$ref":"costs/SEP.csv"},"OCT":{"$ref":"costs/OCT.csv"},"NOV":{"$ref":"costs/NOV.csv"},"DEC":{"$ref":"costs/DEC.csv"}}},
 "bounds":[{"type":"LBC","bound":29.6000003814697},{"type":"UBT","bound": {"$ref":"./UBT.csv"}}],
 "sinks":null,
 "flow":{"$ref" : "flow.csv"}}}
