{"type":"Feature",
 "geometry":{"type":"Point","coordinates":[-120.492091,37.2825698238413]},
 "properties":{"prmname":"WWP402",
 "description":null,
 "type":"Junction",
 "inflows":null,
 "sinks":null,
 "flow":{"$ref" : "flow.csv"}}}
