{"type":"Feature",
 "geometry":{"type":"Point","coordinates":[-121.786569,38.973967]},
 "properties":{"prmname":"HGP04",
 "description":"Hidden node for calibration of GW-4",
 "type":"Junction",
 "inflows":null,
 "sinks":null,
 "flow":{"$ref" : "flow.csv"}}}
