{
  "type": "Feature",
  "geometry": {
    "type": "Point",
    "coordinates": [
      -120.371459148517,
      37.6907930010921
    ]
  },
  "properties": {
    "prmname": "SinkG105",
    "description": "Depletion UPPER MERCED RIVER",
    "type": "Sink",
    "origins": [
      "D643"
    ],
    "terminals": null,
    "inflows": null
  }
}