{"type":"Feature",
 "geometry":{"type":"Point","coordinates":[-120.371459148517,37.6907930010921]},
 "properties":{"prmname":"SinkG103",
 "description":"Depletion EASTSIDE BYPASS",
 "type":"Sink",
 "inflows":null,
 "sinks":null}}
