{"type":"Feature",
 "geometry":{"type":"Point","coordinates":[-120.815047075154,38.1549199429767]},
 "properties":{"prmname":"SR-NHG",
 "description":"New Hogan Lake",
 "type":"Surface Storage",
 "initialstorage":159,
 "endingstorage":92,
 "areacapfactor":0.011182,
 "inflows":null,
 "el_ar_cap":{"$ref":"elevation_area_capacity.csv"},
 "costs":{ "type":"Monthly Variable","costs":{"JAN":{"$ref":"cost_JAN.csv"},"FEB":{"$ref":"cost_FEB.csv"},"MAR":{"$ref":"cost_MAR.csv"},"APR":{"$ref":"cost_APR.csv"},"MAY":{"$ref":"cost_MAY.csv"},"JUN":{"$ref":"cost_JUN.csv"},"JUL":{"$ref":"cost_JUL.csv"},"AUG":{"$ref":"cost_AUG.csv"},"SEP":{"$ref":"cost_SEP.csv"},"OCT":{"$ref":"cost_OCT.csv"},"NOV":{"$ref":"cost_NOV.csv"},"DEC":{"$ref":"cost_DEC.csv"}}},
 "bounds":[{"type":"LBC","bound":17.5},{"type":"UBT","bound": {"$ref":"./UBT.csv"}}],
 "sinks":null}}
