{
  "type": "Feature",
  "geometry": {
    "type": "Point",
    "coordinates": [
      -121.746063612922,
      37.6139319505633
    ]
  },
  "properties": {
    "prmname": "SR-15",
    "description": "Lake Del Valle",
    "type": "Surface Storage",
    "origins": [
      "CN3",
      "DVallePMP"
    ],
    "terminals": [
      "D892"
    ],
    "initialstorage": 28,
    "endingstorage": 24.63,
    "areacapfactor": 0.012203,
    "inflows": null,
    "el_ar_cap": {
      "$ref": "el_ar_cap.csv"
    },
    "costs": {
      "type": "Monthly Variable",
      "costs": [
        {
          "label": "JAN",
          "costs": [
            {
              "capacity": 0,
              "cost": 0.800000011920929
            },
            {
              "capacity": 40,
              "cost": 0
            }
          ]
        },
        {
          "label": "FEB",
          "costs": [
            {
              "capacity": 0,
              "cost": 0.800000011920929
            },
            {
              "capacity": 40,
              "cost": 0
            }
          ]
        },
        {
          "label": "MAR",
          "costs": [
            {
              "capacity": 0,
              "cost": 0.800000011920929
            },
            {
              "capacity": 40,
              "cost": 0
            }
          ]
        },
        {
          "label": "APR",
          "costs": [
            {
              "capacity": 0,
              "cost": 0.800000011920929
            },
            {
              "capacity": 40,
              "cost": 0
            }
          ]
        },
        {
          "label": "MAY",
          "costs": [
            {
              "capacity": 0,
              "cost": 0.800000011920929
            },
            {
              "capacity": 40,
              "cost": 0
            }
          ]
        },
        {
          "label": "JUN",
          "costs": [
            {
              "capacity": 0,
              "cost": 0.800000011920929
            },
            {
              "capacity": 40,
              "cost": 0
            }
          ]
        },
        {
          "label": "JUL",
          "costs": [
            {
              "capacity": 0,
              "cost": 0.800000011920929
            },
            {
              "capacity": 40,
              "cost": 0
            }
          ]
        },
        {
          "label": "AUG",
          "costs": [
            {
              "capacity": 0,
              "cost": 0.800000011920929
            },
            {
              "capacity": 40,
              "cost": 0
            }
          ]
        },
        {
          "label": "SEP",
          "costs": [
            {
              "capacity": 0,
              "cost": 0.800000011920929
            },
            {
              "capacity": 40,
              "cost": 0
            }
          ]
        },
        {
          "label": "OCT",
          "costs": [
            {
              "capacity": 0,
              "cost": 0.800000011920929
            },
            {
              "capacity": 40,
              "cost": 0
            }
          ]
        },
        {
          "label": "NOV",
          "costs": [
            {
              "capacity": 0,
              "cost": 0.800000011920929
            },
            {
              "capacity": 40,
              "cost": 0
            }
          ]
        },
        {
          "label": "DEC",
          "costs": [
            {
              "capacity": 0,
              "cost": 0.800000011920929
            },
            {
              "capacity": 40,
              "cost": 0
            }
          ]
        }
      ]
    },
    "constraints": {
      "constraint_type": "Bounded",
      "lower": {
        "bound_type": "Constant",
        "bound": 9.8
      },
      "upper": {
        "bound_type": "Constant",
        "bound": 40
      }
    }
  }
}