{"type":"Feature",
 "geometry":{"type":"Point","coordinates":[-120.322250928825,37.1290198143843]},
 "properties":{"prmname":"HSU306D645",
 "description":"Hidden node on surface water conveyance channel",
 "type":"Junction",
 "inflows":null,
 "sinks":null,
 "flow":{"$ref" : "flow.csv"}}}
