{"type":"Feature",
 "geometry":{"type":"Point","coordinates":[-120.430029747669,37.2974031561417]},
 "properties":{"prmname":"HSU306D645",
 "description":"Hidden node on surface water conveyance channel",
 "type":"Junction",
 "inflows":null,
 "sinks":null,
 "flow":{"$ref" : "flow.csv"}}}
