{"type":"Feature",
 "geometry":{"type":"Point","coordinates":[-120.342475847159,37.276932152688]},
 "properties":{"prmname":"HSU306D645",
 "description":"Hidden node on surface water conveyance channel",
 "type":"Junction",
 "inflows":null,
 "sinks":null,
 "flow":{"$ref" : "flow.csv"}}}
