{"type":"Feature",
 "geometry":{"type":"Point","coordinates":[-120.317759352405,37.1317055440591]},
 "properties":{"prmname":"HSU306D645",
 "description":"Hidden node on surface water conveyance channel",
 "type":"Junction",
 "inflows":null,
 "sinks":null,
 "flow":{"$ref" : "flow.csv"}}}
