{"type":"Feature",
 "geometry":{"type":"Point","coordinates":[-121.546908746377,37.1214914153249]},
 "properties":{"prmname":"SR-SCAGG",
 "description":"Santa Clara Aggregate",
 "type":"Surface Storage",
 "initialstorage":94,
 "endingstorage":94,
 "areacapfactor":0.020407,
 "inflows":{"default":{"description":"Santa Clara Local inflow","inflow":{"$ref" : "inflow_default.csv"}}},
 "el_ar_cap":{"$ref":"elevation_area_capacity.csv"},
 "costs":{ "type":"Monthly Variable","costs":{"JAN":{"$ref":"cost_JAN.csv"},"FEB":{"$ref":"cost_FEB.csv"},"MAR":{"$ref":"cost_MAR.csv"},"APR":{"$ref":"cost_APR.csv"},"MAY":{"$ref":"cost_MAY.csv"},"JUN":{"$ref":"cost_JUN.csv"},"JUL":{"$ref":"cost_JUL.csv"},"AUG":{"$ref":"cost_AUG.csv"},"SEP":{"$ref":"cost_SEP.csv"},"OCT":{"$ref":"cost_OCT.csv"},"NOV":{"$ref":"cost_NOV.csv"},"DEC":{"$ref":"cost_DEC.csv"}}},
 "bounds":[{"type":"LBC","bound":37},{"type":"UBC","bound":170}],
 "sinks":null}}
