{
  "type": "Feature",
  "geometry": {
    "type": "Point",
    "coordinates": [
      -119.816505707685,
      35.4792814102005
    ]
  },
  "properties": {
    "prmname": "HSU19D847",
    "description": "Hidden node on surface water conveyance channel",
    "type": "Junction",
    "origins": [
      "D847"
    ],
    "terminals": [
      "C100",
      "CVPM19"
    ],
    "inflows": null
  }
}