{"type":"Feature",
 "geometry":{"type":"Point","coordinates":[-116.342767847159,33.7599829213173]},
 "properties":{"prmname":"HSU507C147",
 "description":null,
 "type":"Junction",
 "inflows":null,
 "sinks":null,
 "flow":null}}
