{
  "type": "Feature",
  "geometry": {
    "type": "Point",
    "coordinates": [
      -116.215566847159,
      33.6528799320615
    ]
  },
  "properties": {
    "prmname": "HSU507C147",
    "description": null,
    "type": "Junction",
    "inflows": null,
    "sinks": null,
    "flow": {
      "$ref": "flow.csv"
    }
  }
}