{"type":"Feature",
 "geometry":{"type":"Point","coordinates":[-116.301874548673,33.74896473227]},
 "properties":{"prmname":"HSU507C147",
 "description":null,
 "type":"Junction",
 "inflows":null,
 "sinks":null,
 "flow":null}}
