{"type":"Feature",
 "geometry":{"type":"Point","coordinates":[-116.306366125094,33.731223289165]},
 "properties":{"prmname":"HSU507C147",
 "description":null,
 "type":"Junction",
 "inflows":null,
 "sinks":null,
 "flow":null}}
