{"type":"Feature",
 "geometry":{"type":"Point","coordinates":[-121.51219667916,38.7461430328025]},
 "properties":{"prmname":"HSU204C67",
 "description":"Hidden node on surface water conveyance channel",
 "type":"Junction",
 "inflows":null,
 "sinks":null,
 "flow":null}}
