{
  "type": "Feature",
  "geometry": {
    "type": "Point",
    "coordinates": [
      -121.388785847159,
      38.8339650129794
    ]
  },
  "properties": {
    "prmname": "HSU204C67",
    "description": "Hidden node on surface water conveyance channel",
    "type": "Junction",
    "inflows": null,
    "sinks": null,
    "flow": {
      "$ref": "flow.csv"
    }
  }
}