{"type":"Feature",
 "geometry":{"type":"Point","coordinates":[-119.068722,34.221579]},
 "properties":{"prmname":"HGPVC",
 "description":null,
 "type":"Junction",
 "inflows":null,
 "sinks":null,
 "flow":{"$ref" : "flow.csv"}}}
